{
  "last_updated": "2026-05-21T06:30:42.068836",
  "items": [
    {
      "guid": "https://www.yna.co.kr/view/AKR20260521122500005",
      "source": "연합뉴스_엔터",
      "title": "샤이니 태민, 코첼라 달군 신곡 '퍼미션' 22일 발표",
      "link": "https://www.yna.co.kr/view/AKR20260521122500005",
      "published": "2026-05-21T14:46:43+09:00",
      "summary": "(서울=연합뉴스) 김선우 기자 = 그룹 샤이니 멤버 태민이 오는 22일 새 디지털 싱글 '퍼미션'(PERMISSION)을 발매한다고 소속사 갤럭...",
      "content": "김선우\n기자\n구독\n구독중\n이전\n다음\n이미지 확대\n태민 신곡 '퍼미션' 포스터\n[갤럭시코퍼레이션 제공. 재판매 및 DB 금지]\n(서울=연합뉴스) 김선우 기자 = 그룹 샤이니 멤버 태민이 오는 22일 새 디지털 싱글 '퍼미션'(PERMISSION)을 발매한다고 소속사 갤럭시코퍼레이션이 21일 밝혔다.\n'퍼미션'은 태민이 지난 4월 세계적인 음악 축제 '코첼라' 무대에서 처음으로 선보인 노래다. 스스로 삶을 선택하고 주도하겠다는 태민의 자전적인 이야기를 담았다.\n소속사는 \"태민이 추구하는 예술적 지향점을 확인할 수 있는 곡\"이라고 설명했다.\n태민은 신곡 발표 이후 샤이니 멤버들과 함께 이달 29일부터 31일까지 서울 송파구 올림픽공원 KSPO돔에서 단독 콘서트를 연다.\nsunwoo@yna.co.kr\n제보는 카카오톡 okjebo\n<저작권자(c) 연합뉴스,\n무단 전재-재배포, AI 학습 및 활용 금지>\n2026/05/21 14:46 송고\n2026년05월21일 14시46분 송고\n#태민\n#샤이니\n#퍼미션\n댓글\n좋아요\n슬퍼요\n화나요\n후속요청\n국내 최대 원스톱\n콘텐츠 제공 플랫폼\n함께 보면 좋은 콘텐츠\nby\n데이블\n광고\n함께 읽기 좋은 콘텐츠\nTaboola 후원링크\n광고\n광고\n광고\n연합 마이뉴스\n다양한 주제별 맞춤\n추천 뉴스를 제공합니다.\n북마크\n공유\n공유하기\n카카오톡\n페이스북\nX\n페이스북 메신저\n네이버 밴드\nURL 복사\n닫기\nURL이 복사되었습니다.\n댓글\n글자크기\n본문 글자 크기 조정\n폰트 1단계 13px\n폰트 2단계 16px\n폰트 3단계 18px\n폰트 4단계 20px\n폰트 5단계 22px\n닫기\n프린트\n제보",
      "thumbnail_url": "https://img.yna.co.kr/etc/inner/KR/2026/05/21/AKR20260521122500005_01_i_P2.jpg",
      "category": "K-pop",
      "priority": 1,
      "collected_at": "2026-05-21T06:30:29.517991",
      "status": "unreviewed",
      "evaluated_at": null,
      "score": null,
      "filter_reason": "K-pop 키워드: 싱글, 콘서트"
    },
    {
      "guid": "2026052115025193444",
      "source": "MyDaily_스타",
      "title": "'병역법 위반' 송민호, 증인 출석하나…복무 관리자 \"사전 공모 없었다\" 재차 주장",
      "link": "https://www.mydaily.co.kr/page/view/2026052115025193444",
      "published": "2026-05-21T15:20:19+09:00",
      "summary": "[마이데일리 = 한소희 기자] 그룹 송민호의 병역법 위반 사건과 관련해 함께 재판에 넘겨진 복무 관리자 A씨가 사전 공모 의혹을 거듭 부인했다.\n\n21일 서울서부지방법원 형사10단독 심리로 병역법 위반 혐의를 받는 A씨의 공판이 진행됐다. A씨는 송민호의 사회복무요원 근태를 허위로 관리한 혐의로 기소된 상태다.\n\n이날 A씨 측은 일부 근태 처리 과정에 문제가 있었던 점은 인정하면서도, 송민호와 사전에 공모해 허위 출퇴근 기록을 작성하거나 역할을 나눠 범행을 저지른 것은 아니라는 입장을 밝혔다.\n\n또한 A씨 측은 재판부에 송민호를 증인으로 신청해달라고 요청했다. 재판부는 관련 신청서가 접수되면 채택 여부를 검토하겠다고 밝혔다. 다음 공판은 오는 7월 14일 열릴 예정이다.\n\n송민호는 2023년 3월부터 2024년 12월까지 서울 마포구 시설관리공단에서 사회복무요원으로 대체 복무했다. 그러나 전체 출근일 약 430일 가운데 102일을 무단결근한 혐의를 받고 있다. 이와 함께 정상 출근 후에도 연예 활동 등을 이유로 근무를 제대로 수행하지 않거나 조기 퇴근하는 등 복무를 소홀히 했다는 의혹도 제기됐다.\n\n검찰은 송민호가 실질적인 복무를 하지 않았다고 판단하고 있다. 특히 무단결근 사실을 숨기기 위해 허위 근태 기록이 작성됐다고 보고 송민호에게 징역 1년 6개월을 구형했다.\n\n앞서 송민호는 지난 4월 열린 첫 공판에서 공소사실을 모두 인정했다. 당시 그는 최후진술을 통해 \"모든 분들께 사죄드린다\"며 \"현재 공황장애 치료를 받고 있으며, 건강을 회복해 재복무 기회가 주어진다면 끝까지 성실히 임하겠다\"고 밝혔다.\n\n반면 A씨 측은 첫 공판에 이어 이번 재판에서도 \"송민호와 공모한 사실은 없다\"며 혐의를 일부 부인하고 있다.",
      "content": "[마이데일리 = 한소희 기자] 그룹 송민호의 병역법 위반 사건과 관련해 함께 재판에 넘겨진 복무 관리자 A씨가 사전 공모 의혹을 거듭 부인했다.21일 서울서부지방법원 형사10단독 심리로 병역법 위반 혐의를 받는 A씨의 공판이 진행됐다. A씨는 송민호의 사회복무요원 근태를 허위로 관리한 혐의로 기소된 상태다.이날 A씨 측은 일부 근태 처리 과정에 문제가 있었던 점은 인정하면서도, 송민호와 사전에 공모해 허위 출퇴근 기록을 작성하거나 역할을 나눠 범행을 저지른 것은 아니라는 입장을 밝혔다.또한 A씨 측은 재판부에 송민호를 증인으로 신청해달라고 요청했다. 재판부는 관련 신청서가 접수되면 채택 여부를 검토하겠다고 밝혔다. 다음 공판은 오는 7월 14일 열릴 예정이다.송민호는 2023년 3월부터 2024년 12월까지 서울 마포구 시설관리공단에서 사회복무요원으로 대체 복무했다. 그러나 전체 출근일 약 430일 가운데 102일을 무단결근한 혐의를 받고 있다. 이와 함께 정상 출근 후에도 연예 활동 등을 이유로 근무를 제대로 수행하지 않거나 조기 퇴근하는 등 복무를 소홀히 했다는 의혹도 제기됐다.검찰은 송민호가 실질적인 복무를 하지 않았다고 판단하고 있다. 특히 무단결근 사실을 숨기기 위해 허위 근태 기록이 작성됐다고 보고 송민호에게 징역 1년 6개월을 구형했다.앞서 송민호는 지난 4월 열린 첫 공판에서 공소사실을 모두 인정했다. 당시 그는 최후진술을 통해 \"모든 분들께 사죄드린다\"며 \"현재 공황장애 치료를 받고 있으며, 건강을 회복해 재복무 기회가 주어진다면 끝까지 성실히 임하겠다\"고 밝혔다.반면 A씨 측은 첫 공판에 이어 이번 재판에서도 \"송민호와 공모한 사실은 없다\"며 혐의를 일부 부인하고 있다.많이 본 뉴스\"왜 아이유까지 끌어들여?\"…무차별 폭로 MC몽, 황당한 '물귀신 작전'에 비난 폭발[MD이슈]“이미지 세탁하나” 43억 횡령 황정음, “최고 유튜버 되겠다” 복귀에 싸늘[MD이슈]\"아이 있는 돌싱 원해\" 미혼 박혜경, 솔로 4년 차 '남친'이 꼭 필요한 이유? [물어보살]",
      "thumbnail_url": "https://img.mydaily.co.kr/photos/2026/04/21/2026042111305744626_l.jpg",
      "category": "K-pop",
      "priority": 2,
      "collected_at": "2026-05-21T06:30:39.548470",
      "status": "unreviewed",
      "evaluated_at": null,
      "score": null,
      "filter_reason": "K-pop 키워드: 아이유"
    },
    {
      "guid": "2026052115024762045",
      "source": "MyDaily_스타",
      "title": "\"정경호 父 위해 압구정 빌딩 선물\"…박정수 \"3000만원 명품백, 이해해달라\"",
      "link": "https://www.mydaily.co.kr/page/view/2026052115024762045",
      "published": "2026-05-21T15:02:55+09:00",
      "summary": "[마이데일리 = 곽명동 기자]배우 박정수가 수십 년간 모아온 명품 컬렉션을 공개했다.\n\n지난 20일 유튜브 채널 '웬만해선 정수를 막을 수 없다'에는 '\"이거 팔면 아파트 한 채?!\" 40년 전 타임머신 탄 박정수의 역대급 빈티지 명품 대공개'라는 제목의 영상이 게재됐다.\n\n이날 박정수는 가방, 구두 등 다양한 명품 아이템을 소개하는 시간을 가졌다. 그는 \"대부분 90년대와 2000년대에 구매한 제품들\"이라며, 오랜 기간 정성을 들여 관리해 왔다고 밝혔다.\n\n\n특히 가장 비싼 가방을 묻는 질문에 \"3000만 원짜리\"라고 답해 눈길을 끌었다. 이에 제작진이 \"아까워서 눈도 못 감을 것 같다\"고 농담을 건네자, 박정수는 \"죽을 때가 다 됐는데 뭐가 아깝나. 죽기 전에 (주변에) 주고 가겠다\"라며 쿨한 면모를 보였다.\n\n이어 고가의 명품을 모으게 된 배경도 털어놓았다. 그는 \"당시엔 일만 하던 시기였다\"라며 \"스트레스를 명품을 사면서 풀었던 것 같다. 이걸 사 모으는 재미로 살았으니 이해해달라\"고 솔직하게 고백했다.\n\n한편, 박정수는 지난 1975년 사업가와 결혼해 슬하에 1남 1녀를 두었으나 1997년 이혼했다. 이후 2008년부터 배우 정경호의 아버지인 정을영 PD와 공개 열애를 시작했으며, 현재까지 약 20년간 사실혼 관계를 유지하고 있다.\n\n최근에는 압구정에 건물을 신축한 비하인드를 밝혀 화제를 모으기도 했다. 당시 그는 건물 신축 이유에 대해 \"남편 일하라고 2011년에 지어준 건데, 정작 짓고 나니 일을 안 하고 술만 마시더라\"고 유쾌하게 폭로해 큰 웃음을 안겼다.",
      "content": "[마이데일리 = 곽명동 기자]배우 박정수가 수십 년간 모아온 명품 컬렉션을 공개했다.지난 20일 유튜브 채널 '웬만해선 정수를 막을 수 없다'에는 '\"이거 팔면 아파트 한 채?!\" 40년 전 타임머신 탄 박정수의 역대급 빈티지 명품 대공개'라는 제목의 영상이 게재됐다.이날 박정수는 가방, 구두 등 다양한 명품 아이템을 소개하는 시간을 가졌다. 그는 \"대부분 90년대와 2000년대에 구매한 제품들\"이라며, 오랜 기간 정성을 들여 관리해 왔다고 밝혔다.특히 가장 비싼 가방을 묻는 질문에 \"3000만 원짜리\"라고 답해 눈길을 끌었다. 이에 제작진이 \"아까워서 눈도 못 감을 것 같다\"고 농담을 건네자, 박정수는 \"죽을 때가 다 됐는데 뭐가 아깝나. 죽기 전에 (주변에) 주고 가겠다\"라며 쿨한 면모를 보였다.이어 고가의 명품을 모으게 된 배경도 털어놓았다. 그는 \"당시엔 일만 하던 시기였다\"라며 \"스트레스를 명품을 사면서 풀었던 것 같다. 이걸 사 모으는 재미로 살았으니 이해해달라\"고 솔직하게 고백했다.한편, 박정수는 지난 1975년 사업가와 결혼해 슬하에 1남 1녀를 두었으나 1997년 이혼했다. 이후 2008년부터 배우 정경호의 아버지인 정을영 PD와 공개 열애를 시작했으며, 현재까지 약 20년간 사실혼 관계를 유지하고 있다.최근에는 압구정에 건물을 신축한 비하인드를 밝혀 화제를 모으기도 했다. 당시 그는 건물 신축 이유에 대해 \"남편 일하라고 2011년에 지어준 건데, 정작 짓고 나니 일을 안 하고 술만 마시더라\"고 유쾌하게 폭로해 큰 웃음을 안겼다.많이 본 뉴스\"왜 아이유까지 끌어들여?\"…무차별 폭로 MC몽, 황당한 '물귀신 작전'에 비난 폭발[MD이슈]“이미지 세탁하나” 43억 횡령 황정음, “최고 유튜버 되겠다” 복귀에 싸늘[MD이슈]\"아이 있는 돌싱 원해\" 미혼 박혜경, 솔로 4년 차 '남친'이 꼭 필요한 이유? [물어보살]",
      "thumbnail_url": "https://img.mydaily.co.kr/photos/2026/05/21/2026052115021720218_l.jpg",
      "category": "K-pop",
      "priority": 2,
      "collected_at": "2026-05-21T06:30:39.549537",
      "status": "unreviewed",
      "evaluated_at": null,
      "score": null,
      "filter_reason": "K-pop 키워드: 아이유"
    },
    {
      "guid": "2026052114311765165",
      "source": "MyDaily_스타",
      "title": "걸스데이 소진♥이동하, 신혼 일상 공개…보라색으로 채운 '달달 생일상'",
      "link": "https://www.mydaily.co.kr/page/view/2026052114311765165",
      "published": "2026-05-21T14:55:15+09:00",
      "summary": "[마이데일리 = 한소희 기자] 걸스데이 출신 배우 박소진이 남편 이동하의 특별한 생일 이벤트에 감동한 일상을 공개했다.\n\n소진은 21일 자신의 SNS를 통해 \"가장 사랑하는 남자와 고양이 두 마리만 있으면 매일 행복하다\"며 \"내가 가장 좋아하는 보라색으로 가득 채워준 연보라 케이크와 꽃다발, 보라색 엽서까지 너무 감동이었다\"고 전했다.\n이어 \"꽃 한 송이 한 송이가 다 예뻐서 영상으로 꼼꼼히 남겼다. 최고로 행복한 생일이었다\"며 남편 이동하에게 고마운 마음을 드러냈다.\n\n함께 공개된 사진에는 꽃다발을 든 채 환하게 웃고 있는 소진의 모습이 담겼다. 편안한 잠옷 차림과 민낯에도 자연스러운 행복감이 묻어나 눈길을 끌었다. 특히 이동하가 직접 준비한 것으로 보이는 생일상과 손편지도 시선을 모았다.\n손편지에는 \"사랑하는 아내 소진, 존재해줘서 고마워\"라는 문구가 적혀 있어 훈훈함을 더했다. 이후 이동하가 댓글로 하트 이모티콘을 남기자, 소진은 \"수저까지 보라색이었다\"며 뒤늦게 발견한 디테일에 다시 한번 감동했다.\n달달한 부부의 모습에 배우 이시언은 \"남편분 정말 스윗하다\"는 반응을 남겼고, 방송인 미자 역시 \"마지막 생일상이 감동이다\"라고 댓글을 달았다.\n\n1986년생인 소진은 2010년 그룹 걸스데이 멤버로 데뷔한 뒤 배우로 활동 영역을 넓혔다. 이후 드라마 '스토브리그', '환혼', '더 킹: 영원의 군주' 등 다양한 작품에 출연하며 꾸준히 활동 중이다.\n\n소진과 이동하는 오랜 연애 끝에 지난 2023년 11월 결혼했다. 최근에는 유튜브 채널 '유라유라해'에 출연해 \"원래는 결혼 생각이 없고 결혼이 무섭기도 했다\"면서도 \"지금의 결혼 생활은 정말 행복하다. 결국 누구를 만나느냐가 중요한 것 같다\"며 남편에 대한 애정을 전하기도 했다.",
      "content": "[마이데일리 = 한소희 기자] 걸스데이 출신 배우 박소진이 남편 이동하의 특별한 생일 이벤트에 감동한 일상을 공개했다.소진은 21일 자신의 SNS를 통해 \"가장 사랑하는 남자와 고양이 두 마리만 있으면 매일 행복하다\"며 \"내가 가장 좋아하는 보라색으로 가득 채워준 연보라 케이크와 꽃다발, 보라색 엽서까지 너무 감동이었다\"고 전했다.이어 \"꽃 한 송이 한 송이가 다 예뻐서 영상으로 꼼꼼히 남겼다. 최고로 행복한 생일이었다\"며 남편 이동하에게 고마운 마음을 드러냈다.함께 공개된 사진에는 꽃다발을 든 채 환하게 웃고 있는 소진의 모습이 담겼다. 편안한 잠옷 차림과 민낯에도 자연스러운 행복감이 묻어나 눈길을 끌었다. 특히 이동하가 직접 준비한 것으로 보이는 생일상과 손편지도 시선을 모았다.손편지에는 \"사랑하는 아내 소진, 존재해줘서 고마워\"라는 문구가 적혀 있어 훈훈함을 더했다. 이후 이동하가 댓글로 하트 이모티콘을 남기자, 소진은 \"수저까지 보라색이었다\"며 뒤늦게 발견한 디테일에 다시 한번 감동했다.달달한 부부의 모습에 배우 이시언은 \"남편분 정말 스윗하다\"는 반응을 남겼고, 방송인 미자 역시 \"마지막 생일상이 감동이다\"라고 댓글을 달았다.1986년생인 소진은 2010년 그룹 걸스데이 멤버로 데뷔한 뒤 배우로 활동 영역을 넓혔다. 이후 드라마 '스토브리그', '환혼', '더 킹: 영원의 군주' 등 다양한 작품에 출연하며 꾸준히 활동 중이다.소진과 이동하는 오랜 연애 끝에 지난 2023년 11월 결혼했다. 최근에는 유튜브 채널 '유라유라해'에 출연해 \"원래는 결혼 생각이 없고 결혼이 무섭기도 했다\"면서도 \"지금의 결혼 생활은 정말 행복하다. 결국 누구를 만나느냐가 중요한 것 같다\"며 남편에 대한 애정을 전하기도 했다.많이 본 뉴스\"왜 아이유까지 끌어들여?\"…무차별 폭로 MC몽, 황당한 '물귀신 작전'에 비난 폭발[MD이슈]“이미지 세탁하나” 43억 횡령 황정음, “최고 유튜버 되겠다” 복귀에 싸늘[MD이슈]\"아이 있는 돌싱 원해\" 미혼 박혜경, 솔로 4년 차 '남친'이 꼭 필요한 이유? [물어보살]",
      "thumbnail_url": "https://img.mydaily.co.kr/photos/2026/05/21/2026052114534521756_l.jpg",
      "category": "K-pop",
      "priority": 2,
      "collected_at": "2026-05-21T06:30:39.550429",
      "status": "unreviewed",
      "evaluated_at": null,
      "score": null,
      "filter_reason": "K-pop 키워드: 아이유, 데뷔"
    },
    {
      "guid": "2026052114331109341",
      "source": "MyDaily_스타",
      "title": "투어스, 성장하는 청춘의 표본…\"청춘 다시 일깨워 주고파\"",
      "link": "https://www.mydaily.co.kr/page/view/2026052114331109341",
      "published": "2026-05-21T14:43:57+09:00",
      "summary": "[마이데일리 = 박서연 기자] \"자신이 청춘인 줄 모르는 사람들에게 청춘을 다시 일깨워 주고 싶어요\"\n\n그룹 투어스가 매거진 '디아이콘(DICON)' 34호의 주인공이 됐다. 투어스는 순수한 소년의 얼굴부터 깊어진 청춘의 눈빛까지, 10대에서 20대로 가는 길을 마음껏 펼쳤다.\n\n신유는 \"저희의 가장 자연스러운 모습이 담겼어요. 42들이 평소에 보지 못했던 저희의 모습을 보실 수 있을 거예요!\"라고 자신있게 말했다.\n\n투어스의 성장 서사는 2가지 버전으로 전개됐다. 햇빛 아래의 청량과 네온사인 아래의 몽환을 각각 다른 타입의 176페이지에 담았다.\n\nA타입 타이틀은 '디어 마이 보이후드'(Dear My Boyhood). 투어스의 동심을 소환했다. 강아지와 시간을 보내고, 보드를 타고, 게임기를 두드렸다.\n\n맑은 하늘 아래서 순식간에 어린 시절로 돌아갔다. 카메라를 잊은 채 환하게 웃었다. 서로에게 물을 뿌리고, 장난을 치며 촬영장을 밝은 에너지로 물들였다.\n\nB타입 '타이니 원더 스토리즈'(Tiny Wonder Stories)는 한층 몽환적이다. 네온사인이 빛나는 밤, 청춘의 아지트를 찾았다.\n\n멤버들은 게임을 즐기고, 수다를 나눴다. 동시에, 한층 깊어진 눈빛과 도발적인 미소를 장착했다. 밤이 주는 특유의 나른한 온기를 뿜어냈다.\n\n하이라이트는 유닛 인터뷰다. 형 라인과 막내 라인의 가감없는 입담을 볼 수 있다. 신유·도훈·영재, 한진·지훈·경민이 지금까지 말하지 못했던 이야기를 전했다.\n\n이뿐만 아니라 어느 때보다 진지한 음악 이야기도 들을 수 있다. 멤버들이 정의하는 '보이후드 팝'은 자신들의 성장 이야기였다. \"팬들에게 받은 사랑을 더 크게 돌려주고 싶다\"는 진심도 감동적이다.",
      "content": "[마이데일리 = 박서연 기자]\"자신이 청춘인 줄 모르는 사람들에게 청춘을 다시 일깨워 주고 싶어요\"그룹 투어스가 매거진 '디아이콘(DICON)' 34호의 주인공이 됐다. 투어스는 순수한 소년의 얼굴부터 깊어진 청춘의 눈빛까지, 10대에서 20대로 가는 길을 마음껏 펼쳤다.신유는 \"저희의 가장 자연스러운 모습이 담겼어요. 42들이 평소에 보지 못했던 저희의 모습을 보실 수 있을 거예요!\"라고 자신있게 말했다.투어스의 성장 서사는 2가지 버전으로 전개됐다. 햇빛 아래의 청량과 네온사인 아래의 몽환을 각각 다른 타입의 176페이지에 담았다.A타입 타이틀은 '디어 마이 보이후드'(Dear My Boyhood). 투어스의 동심을 소환했다. 강아지와 시간을 보내고, 보드를 타고, 게임기를 두드렸다.맑은 하늘 아래서 순식간에 어린 시절로 돌아갔다. 카메라를 잊은 채 환하게 웃었다. 서로에게 물을 뿌리고, 장난을 치며 촬영장을 밝은 에너지로 물들였다.B타입 '타이니 원더 스토리즈'(Tiny Wonder Stories)는 한층 몽환적이다. 네온사인이 빛나는 밤, 청춘의 아지트를 찾았다.멤버들은 게임을 즐기고, 수다를 나눴다. 동시에, 한층 깊어진 눈빛과 도발적인 미소를 장착했다. 밤이 주는 특유의 나른한 온기를 뿜어냈다.하이라이트는 유닛 인터뷰다. 형 라인과 막내 라인의 가감없는 입담을 볼 수 있다. 신유·도훈·영재, 한진·지훈·경민이 지금까지 말하지 못했던 이야기를 전했다.이뿐만 아니라 어느 때보다 진지한 음악 이야기도 들을 수 있다. 멤버들이 정의하는 '보이후드 팝'은 자신들의 성장 이야기였다. \"팬들에게 받은 사랑을 더 크게 돌려주고 싶다\"는 진심도 감동적이다.많이 본 뉴스\"왜 아이유까지 끌어들여?\"…무차별 폭로 MC몽, 황당한 '물귀신 작전'에 비난 폭발[MD이슈]“이미지 세탁하나” 43억 횡령 황정음, “최고 유튜버 되겠다” 복귀에 싸늘[MD이슈]\"아이 있는 돌싱 원해\" 미혼 박혜경, 솔로 4년 차 '남친'이 꼭 필요한 이유? [물어보살]",
      "thumbnail_url": "https://img.mydaily.co.kr/photos/2026/05/21/2026052114404048722_l.jpg",
      "category": "K-pop",
      "priority": 2,
      "collected_at": "2026-05-21T06:30:39.551588",
      "status": "unreviewed",
      "evaluated_at": null,
      "score": null,
      "filter_reason": "K-pop 키워드: 아이유, 투어"
    },
    {
      "guid": "2026052114322963899",
      "source": "MyDaily_스타",
      "title": "[MD포토] 드라마 '오십프로' 프로배우 한 자리에",
      "link": "https://www.mydaily.co.kr/page/view/2026052114322963899",
      "published": "2026-05-21T14:32:29+09:00",
      "summary": "[마이데일리 = 한혁승 기자] 배우 이학주, 허성태, 오정세, 신하균, 김신록(왼쪽부터)이 21일 서울 상암동 MBC에서 진행된 드라마 '오십프로' 제작발표회에 참석했다.'오십프로'는 평범해 보여도 끗발 좀 날리던 세 남자가 운명에 의해 다시 움직이게 되는 이야기로, 세상에 치이고 몸은 녹슬었을지언정 의리와 본능만은 여전한 인생의 50%를 달려온 진짜 프로들의 짠물 액션 코미디다.",
      "content": "[마이데일리 = 한혁승 기자] 배우 이학주, 허성태, 오정세, 신하균, 김신록(왼쪽부터)이 21일 서울 상암동 MBC에서 진행된 드라마 '오십프로' 제작발표회에 참석했다.'오십프로'는 평범해 보여도 끗발 좀 날리던 세 남자가 운명에 의해 다시 움직이게 되는 이야기로, 세상에 치이고 몸은 녹슬었을지언정 의리와 본능만은 여전한 인생의 50%를 달려온 진짜 프로들의 짠물 액션 코미디다.많이 본 뉴스\"왜 아이유까지 끌어들여?\"…무차별 폭로 MC몽, 황당한 '물귀신 작전'에 비난 폭발[MD이슈]“이미지 세탁하나” 43억 횡령 황정음, “최고 유튜버 되겠다” 복귀에 싸늘[MD이슈]\"아이 있는 돌싱 원해\" 미혼 박혜경, 솔로 4년 차 '남친'이 꼭 필요한 이유? [물어보살]",
      "thumbnail_url": "https://img.mydaily.co.kr/photos/2026/05/21/2026052114322473599_l.jpg",
      "category": "K-pop",
      "priority": 2,
      "collected_at": "2026-05-21T06:30:39.552310",
      "status": "unreviewed",
      "evaluated_at": null,
      "score": null,
      "filter_reason": "K-pop 키워드: 아이유"
    },
    {
      "guid": "2026052114311636994",
      "source": "MyDaily_스타",
      "title": "[MD포토] 신한균·오정세·허성태 '우리가 오십프로에요'",
      "link": "https://www.mydaily.co.kr/page/view/2026052114311636994",
      "published": "2026-05-21T14:31:16+09:00",
      "summary": "[마이데일리 = 한혁승 기자] 배우 허성태, 오정세, 신하균(왼쪽부터)이 21일 서울 상암동 MBC에서 진행된 드라마 '오십프로' 제작발표회에 참석했다.'오십프로'는 평범해 보여도 끗발 좀 날리던 세 남자가 운명에 의해 다시 움직이게 되는 이야기로, 세상에 치이고 몸은 녹슬었을지언정 의리와 본능만은 여전한 인생의 50%를 달려온 진짜 프로들의 짠물 액션 코미디다.",
      "content": "[마이데일리 = 한혁승 기자] 배우 허성태, 오정세, 신하균(왼쪽부터)이 21일 서울 상암동 MBC에서 진행된 드라마 '오십프로' 제작발표회에 참석했다.'오십프로'는 평범해 보여도 끗발 좀 날리던 세 남자가 운명에 의해 다시 움직이게 되는 이야기로, 세상에 치이고 몸은 녹슬었을지언정 의리와 본능만은 여전한 인생의 50%를 달려온 진짜 프로들의 짠물 액션 코미디다.많이 본 뉴스\"왜 아이유까지 끌어들여?\"…무차별 폭로 MC몽, 황당한 '물귀신 작전'에 비난 폭발[MD이슈]“이미지 세탁하나” 43억 횡령 황정음, “최고 유튜버 되겠다” 복귀에 싸늘[MD이슈]\"아이 있는 돌싱 원해\" 미혼 박혜경, 솔로 4년 차 '남친'이 꼭 필요한 이유? [물어보살]",
      "thumbnail_url": "https://img.mydaily.co.kr/photos/2026/05/21/2026052114311228092_l.jpg",
      "category": "K-pop",
      "priority": 2,
      "collected_at": "2026-05-21T06:30:39.552879",
      "status": "unreviewed",
      "evaluated_at": null,
      "score": null,
      "filter_reason": "K-pop 키워드: 아이유"
    },
    {
      "guid": "2026052114295440768",
      "source": "MyDaily_스타",
      "title": "[MD포토] 박경림 '3년 후 나도 진행 오십프로'",
      "link": "https://www.mydaily.co.kr/page/view/2026052114295440768",
      "published": "2026-05-21T14:29:54+09:00",
      "summary": "[마이데일리 = 한혁승 기자] 방송인 박경림이 21일 서울 상암동 MBC에서 진행된 드라마 '오십프로' 제작발표회에 진행자로 참석했다.'오십프로'는 평범해 보여도 끗발 좀 날리던 세 남자가 운명에 의해 다시 움직이게 되는 이야기로, 세상에 치이고 몸은 녹슬었을지언정 의리와 본능만은 여전한 인생의 50%를 달려온 진짜 프로들의 짠물 액션 코미디다.",
      "content": "[마이데일리 = 한혁승 기자] 방송인 박경림이 21일 서울 상암동 MBC에서 진행된 드라마 '오십프로' 제작발표회에 진행자로 참석했다.'오십프로'는 평범해 보여도 끗발 좀 날리던 세 남자가 운명에 의해 다시 움직이게 되는 이야기로, 세상에 치이고 몸은 녹슬었을지언정 의리와 본능만은 여전한 인생의 50%를 달려온 진짜 프로들의 짠물 액션 코미디다.많이 본 뉴스\"왜 아이유까지 끌어들여?\"…무차별 폭로 MC몽, 황당한 '물귀신 작전'에 비난 폭발[MD이슈]“이미지 세탁하나” 43억 횡령 황정음, “최고 유튜버 되겠다” 복귀에 싸늘[MD이슈]\"아이 있는 돌싱 원해\" 미혼 박혜경, 솔로 4년 차 '남친'이 꼭 필요한 이유? [물어보살]",
      "thumbnail_url": "https://img.mydaily.co.kr/photos/2026/05/21/2026052114280259438_l.jpg",
      "category": "K-pop",
      "priority": 2,
      "collected_at": "2026-05-21T06:30:39.553984",
      "status": "unreviewed",
      "evaluated_at": null,
      "score": null,
      "filter_reason": "K-pop 키워드: 아이유"
    },
    {
      "guid": "2026052114085626486",
      "source": "MyDaily_스타",
      "title": "최고기♥이주은, 혼전임신설 직접 해명…\"피임할 줄 모르냐 악플까지\"",
      "link": "https://www.mydaily.co.kr/page/view/2026052114085626486",
      "published": "2026-05-21T14:29:13+09:00",
      "summary": "[마이데일리 = 한소희 기자] 유튜버 최고기가 예비신부 이주은과 관련해 불거진 혼전 임신설에 대해 직접 해명했다.\n\n지난 20일 유튜브 채널 '최고기의 육아채널'에는 '뭔 또 임신이냐'라는 제목의 영상이 공개됐다. 영상에서 최고기와 이주은은 라이브 방송을 진행하며 각종 질문에 답하는 시간을 가졌다.\n\n이날 한 구독자가 \"결혼식은 언제 하냐\"고 묻자, 이주은은 \"이번 달 말이나 다음 달쯤 결정될 것 같다\"고 밝혔다. 이어 \"진짜 임신한 거냐\"는 질문에는 \"저 임신 안 했다\"고 선을 그었다.\n이에 최고기는 최근 확산된 혼전 임신설에 대해 황당함을 드러냈다. 그는 \"임신했다는 말을 한 번도 한 적이 없는데 기사가 그렇게 나왔다\"며 \"헤드라인을 헷갈리게 바꾸는 건 어느 정도 이해하지만, 말도 안 되는 내용으로 퍼져서 저도 놀랐다\"고 말했다.\n\n이주은 역시 \"요즘 연예인이나 인플루언서 관련 기사들을 잘 믿지 않게 된다\"며 답답한 심경을 털어놨다.\n두 사람은 루머 이후 쏟아진 악성 댓글에 대해서도 언급했다. 최고기는 \"기사 댓글에 '또 임신했냐'는 반응이 많았다\"고 했고, 이주은은 \"'피임할 줄 모르냐', '정관수술 해야 한다' 같은 댓글도 있었다\"며 씁쓸한 반응을 보였다.\n\n현재 함께 생활 중인 이유도 밝혔다. 최고기는 \"처음부터 동거를 한 건 아니었다\"며 \"주은 씨 집 계약이 끝날 시점이어서 집을 알아보던 중, 차라리 같이 지내보자는 이야기가 나와 자연스럽게 함께 살게 됐다\"고 설명했다.\n\n한편, 최고기는 유튜버 유깻잎과 2016년 결혼해 딸 솔잎 양을 얻었지만 2020년 이혼했다. 이후 이주은과 공개 열애를 이어왔으며, 두 사람은 올해 중 결혼식을 올릴 예정이다.",
      "content": "[마이데일리 = 한소희 기자] 유튜버 최고기가 예비신부 이주은과 관련해 불거진 혼전 임신설에 대해 직접 해명했다.지난 20일 유튜브 채널 '최고기의 육아채널'에는 '뭔 또 임신이냐'라는 제목의 영상이 공개됐다. 영상에서 최고기와 이주은은 라이브 방송을 진행하며 각종 질문에 답하는 시간을 가졌다.이날 한 구독자가 \"결혼식은 언제 하냐\"고 묻자, 이주은은 \"이번 달 말이나 다음 달쯤 결정될 것 같다\"고 밝혔다. 이어 \"진짜 임신한 거냐\"는 질문에는 \"저 임신 안 했다\"고 선을 그었다.이에 최고기는 최근 확산된 혼전 임신설에 대해 황당함을 드러냈다. 그는 \"임신했다는 말을 한 번도 한 적이 없는데 기사가 그렇게 나왔다\"며 \"헤드라인을 헷갈리게 바꾸는 건 어느 정도 이해하지만, 말도 안 되는 내용으로 퍼져서 저도 놀랐다\"고 말했다.이주은 역시 \"요즘 연예인이나 인플루언서 관련 기사들을 잘 믿지 않게 된다\"며 답답한 심경을 털어놨다.두 사람은 루머 이후 쏟아진 악성 댓글에 대해서도 언급했다. 최고기는 \"기사 댓글에 '또 임신했냐'는 반응이 많았다\"고 했고, 이주은은 \"'피임할 줄 모르냐', '정관수술 해야 한다' 같은 댓글도 있었다\"며 씁쓸한 반응을 보였다.현재 함께 생활 중인 이유도 밝혔다. 최고기는 \"처음부터 동거를 한 건 아니었다\"며 \"주은 씨 집 계약이 끝날 시점이어서 집을 알아보던 중, 차라리 같이 지내보자는 이야기가 나와 자연스럽게 함께 살게 됐다\"고 설명했다.한편, 최고기는 유튜버 유깻잎과 2016년 결혼해 딸 솔잎 양을 얻었지만 2020년 이혼했다. 이후 이주은과 공개 열애를 이어왔으며, 두 사람은 올해 중 결혼식을 올릴 예정이다.많이 본 뉴스\"왜 아이유까지 끌어들여?\"…무차별 폭로 MC몽, 황당한 '물귀신 작전'에 비난 폭발[MD이슈]“이미지 세탁하나” 43억 횡령 황정음, “최고 유튜버 되겠다” 복귀에 싸늘[MD이슈]\"아이 있는 돌싱 원해\" 미혼 박혜경, 솔로 4년 차 '남친'이 꼭 필요한 이유? [물어보살]",
      "thumbnail_url": "https://img.mydaily.co.kr/photos/2026/05/21/2026052114272236889_l.png",
      "category": "K-pop",
      "priority": 2,
      "collected_at": "2026-05-21T06:30:39.554849",
      "status": "unreviewed",
      "evaluated_at": null,
      "score": null,
      "filter_reason": "K-pop 키워드: 아이유"
    },
    {
      "guid": "2026052114265040224",
      "source": "MyDaily_스타",
      "title": "[전문]\"112만 유튜브 채널, 순식간에 사라져\" …소니와 저작권 문제",
      "link": "https://www.mydaily.co.kr/page/view/2026052114265040224",
      "published": "2026-05-21T14:26:56+09:00",
      "summary": "[마이데일리 = 곽명동 기자]112만 구독자를 보유한 대한민국 1세대 더빙 크리에이터 유준호의 유튜브 채널이 저작권 위반 문제로 삭제됐다.\n\n유준호는 지난 19일 유튜브 채널 커뮤니티를 통해 \"이 채널은 2026년 5월 20일에 삭제될 예정\"이라고 전했다. 매력적인 중저음 목소리와 특유의 기발한 재해석 센스로 오랜 기간 큰 사랑을 받아온 만큼, 이번 채널 삭제 소식은 팬들에게 큰 아쉬움을 남기고 있다.\n\n그는 \"귀멸의 칼날 더빙 영상들에 대해 소니 뮤직 엔터테인먼트 재팬 측이 저작권 권리를 행사했고, 해당 영상들이 삭제되면서 채널 자체가 종료 수순을 밟게 되었다\"며 배경을 설명했다. 이어 \"저작권자가 본인의 권리를 행사하는 건 당연한 일이고, 2차 창작자인 저는 그 결정을 수용해야 하는 위치에 있다\"면서 \"억울하다기보다는, 이만큼 오래 올 수 있었던 게 오히려 운이 좋았다고 생각한다\"고 덧붙였다.\n\n채널 삭제라는 악재 속에서도 그는 연기자로서의 새로운 출발을 알렸다. 유준호는 \"사실 최근엔 더빙에서 벗어나 연기자로서 새로운 걸 시작하고 있는 시점이었다. 어떻게 보면 자연스러운 마무리일지도 모르겠다는 생각도 든다\"라며, \"더빙으로서의 유준호는 여기서 마침표를 찍고, 이제 다른 모습으로 찾아뵙겠다. 응원해 주시길 바란다\"고 끝인사를 전했다.\n\n\n유준호 입장 전문\n\n안녕하세요 유준호 입니다.\n\n현재 이 채널은 2026년 5월 20일에 삭제될 예정입니다.\n\n귀멸의 칼날 더빙 영상들에 대해 Sony Music Entertainment Japan 측이 저작권 권리를 행사했고, 해당 영상들이 삭제되면서 채널 자체가 종료 수순을 밟게 되었습니다.\n\n현재 업로드 기능도 정지된 상태라, 커뮤니티 글로나마 이 상황을 전하게 되었습니다.\n\n소니 측에 선처를 요청하는 메일도 보내보고 다른 방법으로도 연락을 취해보았으나 일주일 안에 해결될 방안을 찾지 못 했습니다.\n\n저작권자가 본인의 권리를 행사하는 건 당연한 일이고, 2차 창작자인 저는 그 결정을 수용해야 하는 위치에 있습니다.\n\n억울하다기보다는, 이만큼 오래 올 수 있었던 게 오히려 운이 좋았다고 생각합니다.\n\n13년 동안 2차 저작물로 콘텐츠를 만들면서,\n\n사실 이 날이 언젠가는 올 수 있는 일이란 걸 항상 알고 있었어서, 막상 닥치고 나니 생각보다 담담하게 받아들여졌습니다.\n\n하지만 그래도 아쉬운 건,\n\n영상마다 달려있는 댓글들입니다.\n\n하나하나 읽으면서 혼자 웃기도 하고, 힘도 많이 받았는데.\n\n그 댓글들이 이 채널과 같이 사라진다는 게, 그게 제일 아깝습니다.\n\n그래서 일주일간 지난 댓글들을 읽으면서 시간을 보냈습니다.\n\n더빙으로 100만을 넘겨보자는 게 오랜 목표였는데,\n\n112만이라는 숫자까지 와있다는 게 아직도 실감이 잘 안 납니다.\n\n지금까지 제 목소리를 들어주셔서 감사했습니다.\n\n사실 최근엔 더빙에서 벗어나 연기자로서 새로운 걸 시작하고 있는 시점이었기도 해서 어떻게 보면 자연스러운 마무리일지도 모르겠다는 생각도 조금 듭니다.\n\n채널 삭제 직후 계정 자체에 연결되어 있는\n\n모든 채널에 대한 기능도 정지될 수 있어서\n\n새롭게 이전 될 채널도 생성하지 않은 상태입니다.\n\n새 채널 관련 소식은 인스타그램에서 가장 먼저 공유할 예정입니다.\n\n(instagram.com/yuferesia)\n\n더빙으로서의 유준호는 여기서 마침표를 찍고,\n\n이제 다른 모습으로 찾아뵙겠습니다.\n\n앞으로의 새로운 활동에 관심 가져주시고,\n\n응원해주시면 감사하겠습니다.\n\n2013. 9. 6 부터 지금까지, 너무 감사했습니다.",
      "content": "[마이데일리 = 곽명동 기자]112만 구독자를 보유한 대한민국 1세대 더빙 크리에이터 유준호의 유튜브 채널이 저작권 위반 문제로 삭제됐다.유준호는 지난 19일 유튜브 채널 커뮤니티를 통해 \"이 채널은 2026년 5월 20일에 삭제될 예정\"이라고 전했다. 매력적인 중저음 목소리와 특유의 기발한 재해석 센스로 오랜 기간 큰 사랑을 받아온 만큼, 이번 채널 삭제 소식은 팬들에게 큰 아쉬움을 남기고 있다.그는 \"귀멸의 칼날 더빙 영상들에 대해 소니 뮤직 엔터테인먼트 재팬 측이 저작권 권리를 행사했고, 해당 영상들이 삭제되면서 채널 자체가 종료 수순을 밟게 되었다\"며 배경을 설명했다. 이어 \"저작권자가 본인의 권리를 행사하는 건 당연한 일이고, 2차 창작자인 저는 그 결정을 수용해야 하는 위치에 있다\"면서 \"억울하다기보다는, 이만큼 오래 올 수 있었던 게 오히려 운이 좋았다고 생각한다\"고 덧붙였다.채널 삭제라는 악재 속에서도 그는 연기자로서의 새로운 출발을 알렸다. 유준호는 \"사실 최근엔 더빙에서 벗어나 연기자로서 새로운 걸 시작하고 있는 시점이었다. 어떻게 보면 자연스러운 마무리일지도 모르겠다는 생각도 든다\"라며, \"더빙으로서의 유준호는 여기서 마침표를 찍고, 이제 다른 모습으로 찾아뵙겠다. 응원해 주시길 바란다\"고 끝인사를 전했다.유준호 입장 전문안녕하세요 유준호 입니다.현재 이 채널은 2026년 5월 20일에 삭제될 예정입니다.귀멸의 칼날 더빙 영상들에 대해 Sony Music Entertainment Japan 측이 저작권 권리를 행사했고, 해당 영상들이 삭제되면서 채널 자체가 종료 수순을 밟게 되었습니다.현재 업로드 기능도 정지된 상태라, 커뮤니티 글로나마 이 상황을 전하게 되었습니다.소니 측에 선처를 요청하는 메일도 보내보고 다른 방법으로도 연락을 취해보았으나 일주일 안에 해결될 방안을 찾지 못 했습니다.저작권자가 본인의 권리를 행사하는 건 당연한 일이고, 2차 창작자인 저는 그 결정을 수용해야 하는 위치에 있습니다.억울하다기보다는, 이만큼 오래 올 수 있었던 게 오히려 운이 좋았다고 생각합니다.13년 동안 2차 저작물로 콘텐츠를 만들면서,사실 이 날이 언젠가는 올 수 있는 일이란 걸 항상 알고 있었어서, 막상 닥치고 나니 생각보다 담담하게 받아들여졌습니다.하지만 그래도 아쉬운 건,영상마다 달려있는 댓글들입니다.하나하나 읽으면서 혼자 웃기도 하고, 힘도 많이 받았는데.그 댓글들이 이 채널과 같이 사라진다는 게, 그게 제일 아깝습니다.그래서 일주일간 지난 댓글들을 읽으면서 시간을 보냈습니다.더빙으로 100만을 넘겨보자는 게 오랜 목표였는데,112만이라는 숫자까지 와있다는 게 아직도 실감이 잘 안 납니다.지금까지 제 목소리를 들어주셔서 감사했습니다.사실 최근엔 더빙에서 벗어나 연기자로서 새로운 걸 시작하고 있는 시점이었기도 해서 어떻게 보면 자연스러운 마무리일지도 모르겠다는 생각도 조금 듭니다.채널 삭제 직후 계정 자체에 연결되어 있는모든 채널에 대한 기능도 정지될 수 있어서새롭게 이전 될 채널도 생성하지 않은 상태입니다.새 채널 관련 소식은 인스타그램에서 가장 먼저 공유할 예정입니다.(instagram.com/yuferesia)더빙으로서의 유준호는 여기서 마침표를 찍고,이제 다른 모습으로 찾아뵙겠습니다.앞으로의 새로운 활동에 관심 가져주시고,응원해주시면 감사하겠습니다.2013. 9. 6 부터 지금까지, 너무 감사했습니다.많이 본 뉴스\"왜 아이유까지 끌어들여?\"…무차별 폭로 MC몽, 황당한 '물귀신 작전'에 비난 폭발[MD이슈]“이미지 세탁하나” 43억 횡령 황정음, “최고 유튜버 되겠다” 복귀에 싸늘[MD이슈]\"아이 있는 돌싱 원해\" 미혼 박혜경, 솔로 4년 차 '남친'이 꼭 필요한 이유? [물어보살]",
      "thumbnail_url": "https://img.mydaily.co.kr/photos/2026/05/21/2026052114254798968_l.jpg",
      "category": "K-pop",
      "priority": 2,
      "collected_at": "2026-05-21T06:30:39.557072",
      "status": "unreviewed",
      "evaluated_at": null,
      "score": null,
      "filter_reason": "K-pop 키워드: 아이유"
    },
    {
      "guid": "2026052114261260652",
      "source": "MyDaily_스타",
      "title": "[MD포토] 한동화 감독 '어쩌면 오정세 역에 더 잘 어울리는 비주얼'",
      "link": "https://www.mydaily.co.kr/page/view/2026052114261260652",
      "published": "2026-05-21T14:26:12+09:00",
      "summary": "[마이데일리 = 한혁승 기자] 한동화 감독이 21일 서울 상암동 MBC에서 진행된 드라마 '오십프로' 제작발표회에 참석했다.'오십프로'는 평범해 보여도 끗발 좀 날리던 세 남자가 운명에 의해 다시 움직이게 되는 이야기로, 세상에 치이고 몸은 녹슬었을지언정 의리와 본능만은 여전한 인생의 50%를 달려온 진짜 프로들의 짠물 액션 코미디다.",
      "content": "[마이데일리 = 한혁승 기자] 한동화 감독이 21일 서울 상암동 MBC에서 진행된 드라마 '오십프로' 제작발표회에 참석했다.'오십프로'는 평범해 보여도 끗발 좀 날리던 세 남자가 운명에 의해 다시 움직이게 되는 이야기로, 세상에 치이고 몸은 녹슬었을지언정 의리와 본능만은 여전한 인생의 50%를 달려온 진짜 프로들의 짠물 액션 코미디다.많이 본 뉴스\"왜 아이유까지 끌어들여?\"…무차별 폭로 MC몽, 황당한 '물귀신 작전'에 비난 폭발[MD이슈]“이미지 세탁하나” 43억 횡령 황정음, “최고 유튜버 되겠다” 복귀에 싸늘[MD이슈]\"아이 있는 돌싱 원해\" 미혼 박혜경, 솔로 4년 차 '남친'이 꼭 필요한 이유? [물어보살]",
      "thumbnail_url": "https://img.mydaily.co.kr/photos/2026/05/21/2026052114260957952_l.jpg",
      "category": "K-pop",
      "priority": 2,
      "collected_at": "2026-05-21T06:30:39.557643",
      "status": "unreviewed",
      "evaluated_at": null,
      "score": null,
      "filter_reason": "K-pop 키워드: 아이유"
    },
    {
      "guid": "2026052114245054475",
      "source": "MyDaily_스타",
      "title": "[MD포토] 이학주 '조직원에서 편의점 직원으로'",
      "link": "https://www.mydaily.co.kr/page/view/2026052114245054475",
      "published": "2026-05-21T14:24:50+09:00",
      "summary": "[마이데일리 = 한혁승 기자] 배우 이학주가 21일 서울 상암동 MBC에서 진행된 드라마 '오십프로' 제작발표회에 참석했다.'오십프로'는 평범해 보여도 끗발 좀 날리던 세 남자가 운명에 의해 다시 움직이게 되는 이야기로, 세상에 치이고 몸은 녹슬었을지언정 의리와 본능만은 여전한 인생의 50%를 달려온 진짜 프로들의 짠물 액션 코미디다.",
      "content": "[마이데일리 = 한혁승 기자] 배우 이학주가 21일 서울 상암동 MBC에서 진행된 드라마 '오십프로' 제작발표회에 참석했다.'오십프로'는 평범해 보여도 끗발 좀 날리던 세 남자가 운명에 의해 다시 움직이게 되는 이야기로, 세상에 치이고 몸은 녹슬었을지언정 의리와 본능만은 여전한 인생의 50%를 달려온 진짜 프로들의 짠물 액션 코미디다.많이 본 뉴스\"왜 아이유까지 끌어들여?\"…무차별 폭로 MC몽, 황당한 '물귀신 작전'에 비난 폭발[MD이슈]“이미지 세탁하나” 43억 횡령 황정음, “최고 유튜버 되겠다” 복귀에 싸늘[MD이슈]\"아이 있는 돌싱 원해\" 미혼 박혜경, 솔로 4년 차 '남친'이 꼭 필요한 이유? [물어보살]",
      "thumbnail_url": "https://img.mydaily.co.kr/photos/2026/05/21/2026052114244891560_l.jpg",
      "category": "K-pop",
      "priority": 2,
      "collected_at": "2026-05-21T06:30:39.558184",
      "status": "unreviewed",
      "evaluated_at": null,
      "score": null,
      "filter_reason": "K-pop 키워드: 아이유"
    },
    {
      "guid": "2026052114235899641",
      "source": "MyDaily_스타",
      "title": "[MD포토] 이학주 '훈훈함 그 자체'",
      "link": "https://www.mydaily.co.kr/page/view/2026052114235899641",
      "published": "2026-05-21T14:23:58+09:00",
      "summary": "[마이데일리 = 한혁승 기자] 배우 이학주가 21일 서울 상암동 MBC에서 진행된 드라마 '오십프로' 제작발표회에 참석했다.'오십프로'는 평범해 보여도 끗발 좀 날리던 세 남자가 운명에 의해 다시 움직이게 되는 이야기로, 세상에 치이고 몸은 녹슬었을지언정 의리와 본능만은 여전한 인생의 50%를 달려온 진짜 프로들의 짠물 액션 코미디다.",
      "content": "[마이데일리 = 한혁승 기자] 배우 이학주가 21일 서울 상암동 MBC에서 진행된 드라마 '오십프로' 제작발표회에 참석했다.'오십프로'는 평범해 보여도 끗발 좀 날리던 세 남자가 운명에 의해 다시 움직이게 되는 이야기로, 세상에 치이고 몸은 녹슬었을지언정 의리와 본능만은 여전한 인생의 50%를 달려온 진짜 프로들의 짠물 액션 코미디다.많이 본 뉴스\"왜 아이유까지 끌어들여?\"…무차별 폭로 MC몽, 황당한 '물귀신 작전'에 비난 폭발[MD이슈]“이미지 세탁하나” 43억 횡령 황정음, “최고 유튜버 되겠다” 복귀에 싸늘[MD이슈]\"아이 있는 돌싱 원해\" 미혼 박혜경, 솔로 4년 차 '남친'이 꼭 필요한 이유? [물어보살]",
      "thumbnail_url": "https://img.mydaily.co.kr/photos/2026/05/21/2026052114235257380_l.jpg",
      "category": "K-pop",
      "priority": 2,
      "collected_at": "2026-05-21T06:30:39.558759",
      "status": "unreviewed",
      "evaluated_at": null,
      "score": null,
      "filter_reason": "K-pop 키워드: 아이유"
    },
    {
      "guid": "2026052114230196068",
      "source": "MyDaily_스타",
      "title": "[MD포토] 김신록 '수사을 즐기는 검사'",
      "link": "https://www.mydaily.co.kr/page/view/2026052114230196068",
      "published": "2026-05-21T14:23:01+09:00",
      "summary": "[마이데일리 = 한혁승 기자] 배우 김신록이 21일 서울 상암동 MBC에서 진행된 드라마 '오십프로' 제작발표회에 참석했다.'오십프로'는 평범해 보여도 끗발 좀 날리던 세 남자가 운명에 의해 다시 움직이게 되는 이야기로, 세상에 치이고 몸은 녹슬었을지언정 의리와 본능만은 여전한 인생의 50%를 달려온 진짜 프로들의 짠물 액션 코미디다.",
      "content": "[마이데일리 = 한혁승 기자] 배우 김신록이 21일 서울 상암동 MBC에서 진행된 드라마 '오십프로' 제작발표회에 참석했다.'오십프로'는 평범해 보여도 끗발 좀 날리던 세 남자가 운명에 의해 다시 움직이게 되는 이야기로, 세상에 치이고 몸은 녹슬었을지언정 의리와 본능만은 여전한 인생의 50%를 달려온 진짜 프로들의 짠물 액션 코미디다.많이 본 뉴스\"왜 아이유까지 끌어들여?\"…무차별 폭로 MC몽, 황당한 '물귀신 작전'에 비난 폭발[MD이슈]“이미지 세탁하나” 43억 횡령 황정음, “최고 유튜버 되겠다” 복귀에 싸늘[MD이슈]\"아이 있는 돌싱 원해\" 미혼 박혜경, 솔로 4년 차 '남친'이 꼭 필요한 이유? [물어보살]",
      "thumbnail_url": "https://img.mydaily.co.kr/photos/2026/05/21/2026052114225753675_l.jpg",
      "category": "K-pop",
      "priority": 2,
      "collected_at": "2026-05-21T06:30:39.559318",
      "status": "unreviewed",
      "evaluated_at": null,
      "score": null,
      "filter_reason": "K-pop 키워드: 아이유"
    },
    {
      "guid": "2026052114215404912",
      "source": "MyDaily_스타",
      "title": "[MD포토] 김신록 '검사로 인사드려요'",
      "link": "https://www.mydaily.co.kr/page/view/2026052114215404912",
      "published": "2026-05-21T14:21:54+09:00",
      "summary": "[마이데일리 = 한혁승 기자] 배우 김신록이 21일 서울 상암동 MBC에서 진행된 드라마 '오십프로' 제작발표회에 참석했다.'오십프로'는 평범해 보여도 끗발 좀 날리던 세 남자가 운명에 의해 다시 움직이게 되는 이야기로, 세상에 치이고 몸은 녹슬었을지언정 의리와 본능만은 여전한 인생의 50%를 달려온 진짜 프로들의 짠물 액션 코미디다.",
      "content": "[마이데일리 = 한혁승 기자] 배우 김신록이 21일 서울 상암동 MBC에서 진행된 드라마 '오십프로' 제작발표회에 참석했다.'오십프로'는 평범해 보여도 끗발 좀 날리던 세 남자가 운명에 의해 다시 움직이게 되는 이야기로, 세상에 치이고 몸은 녹슬었을지언정 의리와 본능만은 여전한 인생의 50%를 달려온 진짜 프로들의 짠물 액션 코미디다.많이 본 뉴스\"왜 아이유까지 끌어들여?\"…무차별 폭로 MC몽, 황당한 '물귀신 작전'에 비난 폭발[MD이슈]“이미지 세탁하나” 43억 횡령 황정음, “최고 유튜버 되겠다” 복귀에 싸늘[MD이슈]\"아이 있는 돌싱 원해\" 미혼 박혜경, 솔로 4년 차 '남친'이 꼭 필요한 이유? [물어보살]",
      "thumbnail_url": "https://img.mydaily.co.kr/photos/2026/05/21/2026052114214934909_l.jpg",
      "category": "K-pop",
      "priority": 2,
      "collected_at": "2026-05-21T06:30:39.559889",
      "status": "unreviewed",
      "evaluated_at": null,
      "score": null,
      "filter_reason": "K-pop 키워드: 아이유"
    },
    {
      "guid": "2026052114201645140",
      "source": "MyDaily_스타",
      "title": "[MD포토] 김신록 '롱부츠 레기룩'",
      "link": "https://www.mydaily.co.kr/page/view/2026052114201645140",
      "published": "2026-05-21T14:20:16+09:00",
      "summary": "[마이데일리 = 한혁승 기자] 배우 김신록이 21일 서울 상암동 MBC에서 진행된 드라마 '오십프로' 제작발표회에 참석했다.'오십프로'는 평범해 보여도 끗발 좀 날리던 세 남자가 운명에 의해 다시 움직이게 되는 이야기로, 세상에 치이고 몸은 녹슬었을지언정 의리와 본능만은 여전한 인생의 50%를 달려온 진짜 프로들의 짠물 액션 코미디다.",
      "content": "[마이데일리 = 한혁승 기자] 배우 김신록이 21일 서울 상암동 MBC에서 진행된 드라마 '오십프로' 제작발표회에 참석했다.'오십프로'는 평범해 보여도 끗발 좀 날리던 세 남자가 운명에 의해 다시 움직이게 되는 이야기로, 세상에 치이고 몸은 녹슬었을지언정 의리와 본능만은 여전한 인생의 50%를 달려온 진짜 프로들의 짠물 액션 코미디다.많이 본 뉴스\"왜 아이유까지 끌어들여?\"…무차별 폭로 MC몽, 황당한 '물귀신 작전'에 비난 폭발[MD이슈]“이미지 세탁하나” 43억 횡령 황정음, “최고 유튜버 되겠다” 복귀에 싸늘[MD이슈]\"아이 있는 돌싱 원해\" 미혼 박혜경, 솔로 4년 차 '남친'이 꼭 필요한 이유? [물어보살]",
      "thumbnail_url": "https://img.mydaily.co.kr/photos/2026/05/21/2026052114201133724_l.jpg",
      "category": "K-pop",
      "priority": 2,
      "collected_at": "2026-05-21T06:30:39.561121",
      "status": "unreviewed",
      "evaluated_at": null,
      "score": null,
      "filter_reason": "K-pop 키워드: 아이유"
    },
    {
      "guid": "2026052114191356741",
      "source": "MyDaily_스타",
      "title": "[MD포토] 허성태 '오십프로 파이팅'",
      "link": "https://www.mydaily.co.kr/page/view/2026052114191356741",
      "published": "2026-05-21T14:19:13+09:00",
      "summary": "[마이데일리 = 한혁승 기자] 배우 허성태가 21일 서울 상암동 MBC에서 진행된 드라마 '오십프로' 제작발표회에 참석했다.'오십프로'는 평범해 보여도 끗발 좀 날리던 세 남자가 운명에 의해 다시 움직이게 되는 이야기로, 세상에 치이고 몸은 녹슬었을지언정 의리와 본능만은 여전한 인생의 50%를 달려온 진짜 프로들의 짠물 액션 코미디다.",
      "content": "[마이데일리 = 한혁승 기자] 배우 허성태가 21일 서울 상암동 MBC에서 진행된 드라마 '오십프로' 제작발표회에 참석했다.'오십프로'는 평범해 보여도 끗발 좀 날리던 세 남자가 운명에 의해 다시 움직이게 되는 이야기로, 세상에 치이고 몸은 녹슬었을지언정 의리와 본능만은 여전한 인생의 50%를 달려온 진짜 프로들의 짠물 액션 코미디다.많이 본 뉴스\"왜 아이유까지 끌어들여?\"…무차별 폭로 MC몽, 황당한 '물귀신 작전'에 비난 폭발[MD이슈]“이미지 세탁하나” 43억 횡령 황정음, “최고 유튜버 되겠다” 복귀에 싸늘[MD이슈]\"아이 있는 돌싱 원해\" 미혼 박혜경, 솔로 4년 차 '남친'이 꼭 필요한 이유? [물어보살]",
      "thumbnail_url": "https://img.mydaily.co.kr/photos/2026/05/21/2026052114190886583_l.jpg",
      "category": "K-pop",
      "priority": 2,
      "collected_at": "2026-05-21T06:30:39.561699",
      "status": "unreviewed",
      "evaluated_at": null,
      "score": null,
      "filter_reason": "K-pop 키워드: 아이유"
    },
    {
      "guid": "2026052114182135221",
      "source": "MyDaily_스타",
      "title": "[MD포토] 허성태 '조직의 2인자'",
      "link": "https://www.mydaily.co.kr/page/view/2026052114182135221",
      "published": "2026-05-21T14:18:21+09:00",
      "summary": "[마이데일리 = 한혁승 기자] 배우 허성태가 21일 서울 상암동 MBC에서 진행된 드라마 '오십프로' 제작발표회에 참석했다.'오십프로'는 평범해 보여도 끗발 좀 날리던 세 남자가 운명에 의해 다시 움직이게 되는 이야기로, 세상에 치이고 몸은 녹슬었을지언정 의리와 본능만은 여전한 인생의 50%를 달려온 진짜 프로들의 짠물 액션 코미디다.",
      "content": "[마이데일리 = 한혁승 기자] 배우 허성태가 21일 서울 상암동 MBC에서 진행된 드라마 '오십프로' 제작발표회에 참석했다.'오십프로'는 평범해 보여도 끗발 좀 날리던 세 남자가 운명에 의해 다시 움직이게 되는 이야기로, 세상에 치이고 몸은 녹슬었을지언정 의리와 본능만은 여전한 인생의 50%를 달려온 진짜 프로들의 짠물 액션 코미디다.많이 본 뉴스\"왜 아이유까지 끌어들여?\"…무차별 폭로 MC몽, 황당한 '물귀신 작전'에 비난 폭발[MD이슈]“이미지 세탁하나” 43억 횡령 황정음, “최고 유튜버 되겠다” 복귀에 싸늘[MD이슈]\"아이 있는 돌싱 원해\" 미혼 박혜경, 솔로 4년 차 '남친'이 꼭 필요한 이유? [물어보살]",
      "thumbnail_url": "https://img.mydaily.co.kr/photos/2026/05/21/2026052114181887614_l.jpg",
      "category": "K-pop",
      "priority": 2,
      "collected_at": "2026-05-21T06:30:39.562240",
      "status": "unreviewed",
      "evaluated_at": null,
      "score": null,
      "filter_reason": "K-pop 키워드: 아이유"
    },
    {
      "guid": "2026052113575725757",
      "source": "MyDaily_스타",
      "title": "'46세' 브라이언, 비혼 결심했나…\"17년째 솔로, 혼자가 익숙해\" [전현무계획3]",
      "link": "https://www.mydaily.co.kr/page/view/2026052113575725757",
      "published": "2026-05-21T14:16:58+09:00",
      "summary": "[마이데일리 = 박로사 기자] 가수 브라이언이 비혼 생각을 밝힌다.\n\n22일(금) 방송되는 MBN·채널S ‘전현무계획3’ 32회에서는 전현무-곽튜브(곽준빈)와 플라이투더스카이 환희-브라이언이 강원도 강릉에서 ‘빨간 맛’ 특집 먹트립을 펼친다.\n\n네 사람은 강릉 중앙시장에 도착하자마자 상인들이 추천한 ‘삼세기(삼숙이)’ 맛집으로 직행한다. 잠시 후 피라냐를 연상케 하는 비주얼의 삼숙이 탕이 등장하자 모두는 얼큰한 국물과 부드러운 생선살의 환상 조합에 푹 빠져 폭풍 먹방을 선보인다.\n\n\n곽튜브는 “아직도 사람들이 화해했냐고 물어보지 않냐”며 플라이투더스카이의 불화설을 조심스레 언급한다. 환희는 “지금은 (사이가) 괜찮아졌냐고 많이들 물으신다”고 쿨하게 인정한 뒤, 과거 무대 직전 다퉜던 일화를 떠올리며 “그때 쓰레기통을 다…”라고 해 궁금증을 폭발시킨다. 이를 듣던 브라이언 역시 곧바로 “여기 소주 한 병 주세요~”라며 능청스럽게 분위기에 기름을 붓고, 환희는 “그래도 무대를 하고 나면 자연스럽게 풀렸다. 어렸을 때라 먹는 걸로도 싸우고 별거 아닌 일로 다퉜다”고 말한다.\n\n\n그러던 중 전현무는 “나는 브라이언이 괜히 반갑다. 왠지 결혼 안 할 것 같아서”라고 묘한 동질감을 드러낸다. 이에 브라이언은 “환희도 안 했는데?”라며 억울해하고, 환희는 “사실 브라이언 꿈이 서른 살 전에 결혼하는 거였다”고 돌발 폭로한다.\n\n그러자 브라이언은 “나이가 들다 보니 혼자가 익숙해졌다. 이젠 영원히 혼자 있어야겠다는 생각도 든다”며 솔로 17년 차라고 말했다. 전현무는 “가끔 썸은 타는데 오래 못 간다”는 환희의 말에 폭풍 공감하더니 “오늘이 축제다!”라며 ‘솔로 만세’를 외쳐 현장을 웃음바다로 만든다.\n\n환희와 브라이언이 출연하는 MBN·채널S ‘전현무계획3’ 32회는 22일(금) 밤 9시 10분 방송된다.",
      "content": "[마이데일리 = 박로사 기자] 가수 브라이언이 비혼 생각을 밝힌다.22일(금) 방송되는 MBN·채널S ‘전현무계획3’ 32회에서는 전현무-곽튜브(곽준빈)와 플라이투더스카이 환희-브라이언이 강원도 강릉에서 ‘빨간 맛’ 특집 먹트립을 펼친다.네 사람은 강릉 중앙시장에 도착하자마자 상인들이 추천한 ‘삼세기(삼숙이)’ 맛집으로 직행한다. 잠시 후 피라냐를 연상케 하는 비주얼의 삼숙이 탕이 등장하자 모두는 얼큰한 국물과 부드러운 생선살의 환상 조합에 푹 빠져 폭풍 먹방을 선보인다.곽튜브는 “아직도 사람들이 화해했냐고 물어보지 않냐”며 플라이투더스카이의 불화설을 조심스레 언급한다. 환희는 “지금은 (사이가) 괜찮아졌냐고 많이들 물으신다”고 쿨하게 인정한 뒤, 과거 무대 직전 다퉜던 일화를 떠올리며 “그때 쓰레기통을 다…”라고 해 궁금증을 폭발시킨다. 이를 듣던 브라이언 역시 곧바로 “여기 소주 한 병 주세요~”라며 능청스럽게 분위기에 기름을 붓고, 환희는 “그래도 무대를 하고 나면 자연스럽게 풀렸다. 어렸을 때라 먹는 걸로도 싸우고 별거 아닌 일로 다퉜다”고 말한다.그러던 중 전현무는 “나는 브라이언이 괜히 반갑다. 왠지 결혼 안 할 것 같아서”라고 묘한 동질감을 드러낸다. 이에 브라이언은 “환희도 안 했는데?”라며 억울해하고, 환희는 “사실 브라이언 꿈이 서른 살 전에 결혼하는 거였다”고 돌발 폭로한다.그러자 브라이언은 “나이가 들다 보니 혼자가 익숙해졌다. 이젠 영원히 혼자 있어야겠다는 생각도 든다”며 솔로 17년 차라고 말했다. 전현무는 “가끔 썸은 타는데 오래 못 간다”는 환희의 말에 폭풍 공감하더니 “오늘이 축제다!”라며 ‘솔로 만세’를 외쳐 현장을 웃음바다로 만든다.환희와 브라이언이 출연하는 MBN·채널S ‘전현무계획3’ 32회는 22일(금) 밤 9시 10분 방송된다.많이 본 뉴스\"왜 아이유까지 끌어들여?\"…무차별 폭로 MC몽, 황당한 '물귀신 작전'에 비난 폭발[MD이슈]“이미지 세탁하나” 43억 횡령 황정음, “최고 유튜버 되겠다” 복귀에 싸늘[MD이슈]\"아이 있는 돌싱 원해\" 미혼 박혜경, 솔로 4년 차 '남친'이 꼭 필요한 이유? [물어보살]",
      "thumbnail_url": "https://img.mydaily.co.kr/photos/2026/05/21/2026052114123082605_l.jpg",
      "category": "K-pop",
      "priority": 2,
      "collected_at": "2026-05-21T06:30:39.563122",
      "status": "unreviewed",
      "evaluated_at": null,
      "score": null,
      "filter_reason": "K-pop 키워드: 아이유"
    },
    {
      "guid": "2026052114160365389",
      "source": "MyDaily_스타",
      "title": "[MD포토] 오정세 '북한특수공작원이 선보이는 택견'",
      "link": "https://www.mydaily.co.kr/page/view/2026052114160365389",
      "published": "2026-05-21T14:16:04+09:00",
      "summary": "[마이데일리 = 한혁승 기자] 배우 오정세가 21일 서울 상암동 MBC에서 진행된 드라마 '오십프로' 제작발표회에 참석했다.'오십프로'는 평범해 보여도 끗발 좀 날리던 세 남자가 운명에 의해 다시 움직이게 되는 이야기로, 세상에 치이고 몸은 녹슬었을지언정 의리와 본능만은 여전한 인생의 50%를 달려온 진짜 프로들의 짠물 액션 코미디다.",
      "content": "[마이데일리 = 한혁승 기자] 배우 오정세가 21일 서울 상암동 MBC에서 진행된 드라마 '오십프로' 제작발표회에 참석했다.'오십프로'는 평범해 보여도 끗발 좀 날리던 세 남자가 운명에 의해 다시 움직이게 되는 이야기로, 세상에 치이고 몸은 녹슬었을지언정 의리와 본능만은 여전한 인생의 50%를 달려온 진짜 프로들의 짠물 액션 코미디다.많이 본 뉴스\"왜 아이유까지 끌어들여?\"…무차별 폭로 MC몽, 황당한 '물귀신 작전'에 비난 폭발[MD이슈]“이미지 세탁하나” 43억 횡령 황정음, “최고 유튜버 되겠다” 복귀에 싸늘[MD이슈]\"아이 있는 돌싱 원해\" 미혼 박혜경, 솔로 4년 차 '남친'이 꼭 필요한 이유? [물어보살]",
      "thumbnail_url": "https://img.mydaily.co.kr/photos/2026/05/21/2026052114155999584_l.jpg",
      "category": "K-pop",
      "priority": 2,
      "collected_at": "2026-05-21T06:30:39.563689",
      "status": "unreviewed",
      "evaluated_at": null,
      "score": null,
      "filter_reason": "K-pop 키워드: 아이유"
    },
    {
      "guid": "2026052114142132915",
      "source": "MyDaily_스타",
      "title": "[MD포토] 오정세 '걸음도 택견 느낌'",
      "link": "https://www.mydaily.co.kr/page/view/2026052114142132915",
      "published": "2026-05-21T14:14:21+09:00",
      "summary": "[마이데일리 = 한혁승 기자] 배우 오정세가 21일 서울 상암동 MBC에서 진행된 드라마 '오십프로' 제작발표회에 참석했다.'오십프로'는 평범해 보여도 끗발 좀 날리던 세 남자가 운명에 의해 다시 움직이게 되는 이야기로, 세상에 치이고 몸은 녹슬었을지언정 의리와 본능만은 여전한 인생의 50%를 달려온 진짜 프로들의 짠물 액션 코미디다.",
      "content": "[마이데일리 = 한혁승 기자] 배우 오정세가 21일 서울 상암동 MBC에서 진행된 드라마 '오십프로' 제작발표회에 참석했다.'오십프로'는 평범해 보여도 끗발 좀 날리던 세 남자가 운명에 의해 다시 움직이게 되는 이야기로, 세상에 치이고 몸은 녹슬었을지언정 의리와 본능만은 여전한 인생의 50%를 달려온 진짜 프로들의 짠물 액션 코미디다.많이 본 뉴스\"왜 아이유까지 끌어들여?\"…무차별 폭로 MC몽, 황당한 '물귀신 작전'에 비난 폭발[MD이슈]“이미지 세탁하나” 43억 횡령 황정음, “최고 유튜버 되겠다” 복귀에 싸늘[MD이슈]\"아이 있는 돌싱 원해\" 미혼 박혜경, 솔로 4년 차 '남친'이 꼭 필요한 이유? [물어보살]",
      "thumbnail_url": "https://img.mydaily.co.kr/photos/2026/05/21/2026052114141688475_l.jpg",
      "category": "K-pop",
      "priority": 2,
      "collected_at": "2026-05-21T06:30:39.564830",
      "status": "unreviewed",
      "evaluated_at": null,
      "score": null,
      "filter_reason": "K-pop 키워드: 아이유"
    },
    {
      "guid": "2026052114130753395",
      "source": "MyDaily_스타",
      "title": "[MD포토] 신하균 '총 든 국정원'",
      "link": "https://www.mydaily.co.kr/page/view/2026052114130753395",
      "published": "2026-05-21T14:13:07+09:00",
      "summary": "[마이데일리 = 한혁승 기자] 배우 신하균이 21일 서울 상암동 MBC에서 진행된 드라마 '오십프로' 제작발표회에 참석했다.'오십프로'는 평범해 보여도 끗발 좀 날리던 세 남자가 운명에 의해 다시 움직이게 되는 이야기로, 세상에 치이고 몸은 녹슬었을지언정 의리와 본능만은 여전한 인생의 50%를 달려온 진짜 프로들의 짠물 액션 코미디다.",
      "content": "[마이데일리 = 한혁승 기자] 배우 신하균이 21일 서울 상암동 MBC에서 진행된 드라마 '오십프로' 제작발표회에 참석했다.'오십프로'는 평범해 보여도 끗발 좀 날리던 세 남자가 운명에 의해 다시 움직이게 되는 이야기로, 세상에 치이고 몸은 녹슬었을지언정 의리와 본능만은 여전한 인생의 50%를 달려온 진짜 프로들의 짠물 액션 코미디다.많이 본 뉴스\"왜 아이유까지 끌어들여?\"…무차별 폭로 MC몽, 황당한 '물귀신 작전'에 비난 폭발[MD이슈]“이미지 세탁하나” 43억 횡령 황정음, “최고 유튜버 되겠다” 복귀에 싸늘[MD이슈]\"아이 있는 돌싱 원해\" 미혼 박혜경, 솔로 4년 차 '남친'이 꼭 필요한 이유? [물어보살]",
      "thumbnail_url": "https://img.mydaily.co.kr/photos/2026/05/21/2026052114130505350_l.jpg",
      "category": "K-pop",
      "priority": 2,
      "collected_at": "2026-05-21T06:30:39.565555",
      "status": "unreviewed",
      "evaluated_at": null,
      "score": null,
      "filter_reason": "K-pop 키워드: 아이유"
    },
    {
      "guid": "2026052113442834281",
      "source": "MyDaily_스타",
      "title": "장영란, 알고 보니 엘리트 집안…\"父 전교 1등 출신 경찰 공무원, 오빠는 교수\"",
      "link": "https://www.mydaily.co.kr/page/view/2026052113442834281",
      "published": "2026-05-21T14:07:32+09:00",
      "summary": "[마이데일리 = 한소희 기자] 방송인 장영란이 숨겨진 '브레인 집안' 면모를 공개했다. 경찰 공무원이었던 아버지는 학창 시절 전교 1등 출신이었고, 오빠는 대학교수로 재직 중인 사실이 알려져 놀라움을 안겼다.\n\n지난 20일 유튜브 채널 'A급 장영란'에는 '연예인 엄마, 한의사 아빠 둔 장영란 아들딸이 물려받지 못한 충격적 재능?'이라는 제목의 영상이 게재됐다.\n\n영상 속 장영란은 남편 한창, 딸 지우, 아들 준우와 함께 지문 적성 검사를 받기 위해 전문 기관을 찾았다. 그는 \"요즘 학부모들 사이에서 아이 성향과 적성에 대한 관심이 많다\"며 \"아이들이 어떤 직업과 잘 맞는지 궁금해서 검사를 받아보게 됐다\"고 설명했다.\n\n이어 \"딸은 중학교 1학년, 아들은 초등학교 6학년이다 보니 부모 입장에서 고민이 많아진다\"며 자녀 진로에 대한 현실적인 고민도 털어놨다.\n검사를 진행하던 중 장영란은 자신의 집안 이야기를 꺼냈다. 그는 \"나도 머리가 나쁜 편은 아니다\"라며 \"아버지가 가평고 시절 전교 1등을 하셨다\"고 자랑했다. 특히 장영란의 아버지가 경찰 공무원으로 재직했다는 사실과 함께, 오빠가 현재 대학교 교수로 활동 중이라는 점까지 알려지며 반전 가족 스펙이 화제를 모았다.\n앞서 장영란은 자신의 유튜브를 통해 자동차공학과 교수로 재직 중인 오빠를 공개한 바 있다. 당시 그는 \"오빠는 어릴 때부터 공부가 재능인 사람이었다\"며 남다른 학구열을 전하기도 했다.\n이날 공개된 지문 검사 결과에서 장영란은 '감성형' 성향으로 분석됐다. 전문가에 따르면 그는 감정을 숨기지 못하고 솔직하게 표현하는 타입이며, 한 가지에 몰입하는 능력이 뛰어난 '수재형' 특성을 지녔다고.\n\n전문가는 \"정확한 방법을 배우면 빠르게 습득하고 집중력도 뛰어난 편\"이라며 \"이런 유형은 대체로 공부를 잘하는 경우가 많다\"고 설명했다.\n\n결과를 들은 장영란은 \"너무 신기하다\"며 만족스러운 반응을 보였다. 또 검사에서는 교사, 가수, 연기자, 국악인 등이 장영란과 잘 어울리는 직업군으로 제시돼 눈길을 끌었다.\n\n한편, 장영란은 검사 후 \"아버지가 경찰 공무원이었는데 이런 성향도 영향을 받는 거냐\"고 질문했고, 전문가는 \"유전적 영향이 있을 수 있다\"고 답했다.",
      "content": "[마이데일리 = 한소희 기자] 방송인 장영란이 숨겨진 '브레인 집안' 면모를 공개했다. 경찰 공무원이었던 아버지는 학창 시절 전교 1등 출신이었고, 오빠는 대학교수로 재직 중인 사실이 알려져 놀라움을 안겼다.지난 20일 유튜브 채널 'A급 장영란'에는 '연예인 엄마, 한의사 아빠 둔 장영란 아들딸이 물려받지 못한 충격적 재능?'이라는 제목의 영상이 게재됐다.영상 속 장영란은 남편 한창, 딸 지우, 아들 준우와 함께 지문 적성 검사를 받기 위해 전문 기관을 찾았다. 그는 \"요즘 학부모들 사이에서 아이 성향과 적성에 대한 관심이 많다\"며 \"아이들이 어떤 직업과 잘 맞는지 궁금해서 검사를 받아보게 됐다\"고 설명했다.이어 \"딸은 중학교 1학년, 아들은 초등학교 6학년이다 보니 부모 입장에서 고민이 많아진다\"며 자녀 진로에 대한 현실적인 고민도 털어놨다.검사를 진행하던 중 장영란은 자신의 집안 이야기를 꺼냈다. 그는 \"나도 머리가 나쁜 편은 아니다\"라며 \"아버지가 가평고 시절 전교 1등을 하셨다\"고 자랑했다. 특히 장영란의 아버지가 경찰 공무원으로 재직했다는 사실과 함께, 오빠가 현재 대학교 교수로 활동 중이라는 점까지 알려지며 반전 가족 스펙이 화제를 모았다.앞서 장영란은 자신의 유튜브를 통해 자동차공학과 교수로 재직 중인 오빠를 공개한 바 있다. 당시 그는 \"오빠는 어릴 때부터 공부가 재능인 사람이었다\"며 남다른 학구열을 전하기도 했다.이날 공개된 지문 검사 결과에서 장영란은 '감성형' 성향으로 분석됐다. 전문가에 따르면 그는 감정을 숨기지 못하고 솔직하게 표현하는 타입이며, 한 가지에 몰입하는 능력이 뛰어난 '수재형' 특성을 지녔다고.전문가는 \"정확한 방법을 배우면 빠르게 습득하고 집중력도 뛰어난 편\"이라며 \"이런 유형은 대체로 공부를 잘하는 경우가 많다\"고 설명했다.결과를 들은 장영란은 \"너무 신기하다\"며 만족스러운 반응을 보였다. 또 검사에서는 교사, 가수, 연기자, 국악인 등이 장영란과 잘 어울리는 직업군으로 제시돼 눈길을 끌었다.한편, 장영란은 검사 후 \"아버지가 경찰 공무원이었는데 이런 성향도 영향을 받는 거냐\"고 질문했고, 전문가는 \"유전적 영향이 있을 수 있다\"고 답했다.많이 본 뉴스\"왜 아이유까지 끌어들여?\"…무차별 폭로 MC몽, 황당한 '물귀신 작전'에 비난 폭발[MD이슈]“이미지 세탁하나” 43억 횡령 황정음, “최고 유튜버 되겠다” 복귀에 싸늘[MD이슈]\"아이 있는 돌싱 원해\" 미혼 박혜경, 솔로 4년 차 '남친'이 꼭 필요한 이유? [물어보살]",
      "thumbnail_url": "https://img.mydaily.co.kr/photos/2026/05/21/2026052114033682809_l.png",
      "category": "K-pop",
      "priority": 2,
      "collected_at": "2026-05-21T06:30:39.568121",
      "status": "unreviewed",
      "evaluated_at": null,
      "score": null,
      "filter_reason": "K-pop 키워드: 아이유"
    },
    {
      "guid": "2026052113564492496",
      "source": "MyDaily_스타",
      "title": "MC몽 \"김민종 측, 거금 주고 거짓 증언 할 화류계 여자 찾고 있더라\"…2차 폭로",
      "link": "https://www.mydaily.co.kr/page/view/2026052113564492496",
      "published": "2026-05-21T14:03:00+09:00",
      "summary": "[마이데일리 = 서기찬 기자] 가수 MC몽(본명 신동현)의 거침없는 연쇄 폭로가 연예계를 걷잡을 수 없는 혼란으로 몰아넣고 있다.\n\n수십억 원대 불법 도박 모임의 일원으로 배우 김민종을 공개 저격한 데 이어, 이번에는 상대 측이 자신을 매장하기 위해 유흥업계 종사자들을 매수하려 했다는 충격적인 주장까지 들고 나왔다.\n\n사태의 발단은 지난 18일 진행된 MC몽의 개인 SNS 라이브 방송이었다. 그는 이 자리에서 연예계 불법 도박 모임인 이른바 ‘바둑이’의 존재를 폭로하며 김민종의 실명을 거론했다.\n\n더불어 건설업자 에테르노 차준영 회장을 비롯한 박 회장, 이 회장, 최 대표, 안 대표 등 거물급 인사들과 연예인들이 얽혀있다고 전했다.\n\n여기에 일본 원정 도박 배우, 한 그룹 회장 친척과 중년 여배우의 비밀 교제 등 미확인 루머들을 쏟아냈으나, 이를 뒷받침할 만한 명확한 물증은 제시하지 않았다.\n\n근거 없는 난타전에 김민종과 그의 법률대리인 법무법인 오킴스는 즉각 강경 대응을 선언했다. 이들은 “명백한 허위사실이다. 당당함을 입증하기 위해 어떠한 타협도 없이 정면 돌파할 거다. 필요한 부분에 대해서는 민형사상 법적 책임을 물을 예정”이라며 강하게 받아쳤다.\n\n하지만 MC몽의 독설은 멈추지 않았다. 첫 방송 당시 부적절한 단어 사용으로 계정이 일주일 간 차단당하자, 곧바로 새 부계정을 파고 이튿날인 19일 또다시 방송을 켰다.\n\n특히 이날 방송에서 MC몽은 김민종과 차준영(원헌드레드 차가원 회장의 작은아버지), 김호중 전 소속사 대표를 싸잡아 비판하며 음해 공작 의혹을 제기했다.\n\n그는 “이 무리가 무엇을 시도했냐면, 내 주위에 있는 여성분들, 아니면 전혀 모르는 여성분들에게, 그리고 화류계에 종사하는 여성분들에게도 거금을 줄테니 MC몽에 대한 아는 것들, 혹은 지어낼 수 있는 이야기들을 해줄 사람들을 찾고 있더라”고 주장했다.\n\n이와 함께 MC몽은 언론이 자신의 활동 정지 사유를 본질과 다르게 다루고 있다며 “논점을 흐트리는 것을 보고 대단하다고 느꼈다”고 불쾌감을 감추지 않았다.\n\n상대의 도발에 단호하게 맞서던 김민종 측은, 화류계 여성을 동원한 폭로 조작 의혹이라는 황당한 2차 공세에 대해서는 현재까지 이렇다 할 공식적인 해명이나 반박을 내놓지 않은 상태다.\n\n이전투구 양상으로 번진 두 스타의 진실공방이 어떻게 가려질지 대중의 시선이 집중되고 있다.",
      "content": "[마이데일리 = 서기찬 기자] 가수 MC몽(본명 신동현)의 거침없는 연쇄 폭로가 연예계를 걷잡을 수 없는 혼란으로 몰아넣고 있다.수십억 원대 불법 도박 모임의 일원으로 배우 김민종을 공개 저격한 데 이어, 이번에는 상대 측이 자신을 매장하기 위해 유흥업계 종사자들을 매수하려 했다는 충격적인 주장까지 들고 나왔다.사태의 발단은 지난 18일 진행된 MC몽의 개인 SNS 라이브 방송이었다. 그는 이 자리에서 연예계 불법 도박 모임인 이른바 ‘바둑이’의 존재를 폭로하며 김민종의 실명을 거론했다.더불어 건설업자 에테르노 차준영 회장을 비롯한 박 회장, 이 회장, 최 대표, 안 대표 등 거물급 인사들과 연예인들이 얽혀있다고 전했다.여기에 일본 원정 도박 배우, 한 그룹 회장 친척과 중년 여배우의 비밀 교제 등 미확인 루머들을 쏟아냈으나, 이를 뒷받침할 만한 명확한 물증은 제시하지 않았다.근거 없는 난타전에 김민종과 그의 법률대리인 법무법인 오킴스는 즉각 강경 대응을 선언했다. 이들은 “명백한 허위사실이다. 당당함을 입증하기 위해 어떠한 타협도 없이 정면 돌파할 거다. 필요한 부분에 대해서는 민형사상 법적 책임을 물을 예정”이라며 강하게 받아쳤다.하지만 MC몽의 독설은 멈추지 않았다. 첫 방송 당시 부적절한 단어 사용으로 계정이 일주일 간 차단당하자, 곧바로 새 부계정을 파고 이튿날인 19일 또다시 방송을 켰다.특히 이날 방송에서 MC몽은 김민종과 차준영(원헌드레드 차가원 회장의 작은아버지), 김호중 전 소속사 대표를 싸잡아 비판하며 음해 공작 의혹을 제기했다.그는 “이 무리가 무엇을 시도했냐면, 내 주위에 있는 여성분들, 아니면 전혀 모르는 여성분들에게, 그리고 화류계에 종사하는 여성분들에게도 거금을 줄테니 MC몽에 대한 아는 것들, 혹은 지어낼 수 있는 이야기들을 해줄 사람들을 찾고 있더라”고 주장했다.이와 함께 MC몽은 언론이 자신의 활동 정지 사유를 본질과 다르게 다루고 있다며 “논점을 흐트리는 것을 보고 대단하다고 느꼈다”고 불쾌감을 감추지 않았다.상대의 도발에 단호하게 맞서던 김민종 측은, 화류계 여성을 동원한 폭로 조작 의혹이라는 황당한 2차 공세에 대해서는 현재까지 이렇다 할 공식적인 해명이나 반박을 내놓지 않은 상태다.이전투구 양상으로 번진 두 스타의 진실공방이 어떻게 가려질지 대중의 시선이 집중되고 있다.많이 본 뉴스\"왜 아이유까지 끌어들여?\"…무차별 폭로 MC몽, 황당한 '물귀신 작전'에 비난 폭발[MD이슈]“이미지 세탁하나” 43억 횡령 황정음, “최고 유튜버 되겠다” 복귀에 싸늘[MD이슈]\"아이 있는 돌싱 원해\" 미혼 박혜경, 솔로 4년 차 '남친'이 꼭 필요한 이유? [물어보살]",
      "thumbnail_url": "https://img.mydaily.co.kr/photos/2026/05/19/2026051905592252295_l.jpg",
      "category": "K-pop",
      "priority": 2,
      "collected_at": "2026-05-21T06:30:39.569864",
      "status": "unreviewed",
      "evaluated_at": null,
      "score": null,
      "filter_reason": "K-pop 키워드: 아이유"
    },
    {
      "guid": "2026052113371329772",
      "source": "MyDaily_스타",
      "title": "'류필립♥' 미나, 용종 7개 떼더니 결국…남양주 집에 헬스장 차렸다 [마데핫리뷰]",
      "link": "https://www.mydaily.co.kr/page/view/2026052113371329772",
      "published": "2026-05-21T14:00:45+09:00",
      "summary": "[마이데일리 = 강다윤 기자] 가수 미나(54·심민아)가 건강검진 결과를 공개했다.\n\n20일 유튜브 채널 'Feelme 필미커플'에는 '의사도 놀란 55세 가수 미나의 충격적인 건강검진 결과는 어땠길래..?'라는 제목의 영상이 업로드됐다.\n공개된 영상에서 미나는 새벽 5시 30분부터 건강검진 준비에 나섰다. 그는 \"2년 만에 위내시경이랑 대장내시경을 하기로 해서 대장약을 먹으려고 일어났다. 물 네 잔인데 너무 힘들다. 못 잘 것 같다\"고 토로했다.\n\n남편 류필립(37·박필립)이 운전하는 차를 타고 병원으로 향하던 미나는 \"40대 넘어서 건강검진을 받기 시작했다. 아빠가 내가 37, 38살 때 돌아가셨다. 그래서 건강검진을 시작했고, 2년 전에 엄마가 돌아가시니까 이제 내가 50대 중반이 되니 곧 내 차례라는 생각이 들더라\"고 털어놨다.\n\n이어 \"그저께 갑자기 심장이 찌릿찌릿한 것 같아 무서워서 병원에 가 심전도랑 심장 초음파까지 다 받았다. 그런데 너무 튼튼하다고 하더라. 심장으로 흐르는 피가 너무 깨끗하고 튼튼하다고 했다\"고 멋쩍게 웃었다.\n\n식단과 운동에 대한 솔직한 생각도 밝혔다. 미나는 \"안 좋은 음식을 많이 먹는다. 중국 활동할 때 기름진 걸 얼마나 많이 먹었겠나. 그땐 젊어서 운동도 잘 못 했다\"며 \"이제는 확실히 50대가 되니까 운동이 살길이다. 몸매 관리보다는 건강, 죽기 싫어서 운동하는 것\"이라고 말했다.\n\n그러면서 \"어제 하루 흰죽만 먹으면서 느낀 게 식단은 못 하겠다는 거다. 일단 많이 먹어야 한다. 그래도 못 먹는 여자보다 낫지 않냐\"고 너스레를 떨었다. 이를 들은 류필립은 \"잘 먹고 운동 잘하는 게 제일 좋다\"고 맞장구쳤다.\n\n병원에 도착한 미나는 혈압부터 쟀다. 107, 63이라과가 나온 가운데 그는 \"1년 전에 고지혈증 조심하라고 경과를 보자고 했고, 간종양 때문에 6개월 후 초음파, 복부 초음파도 6개월마다 하라고 했다. 그런데 6개월마다 못 왔다\"고 설명했다.\n\n류필립은 \"여보가 그게 많더라. 용종이 많아서\"라며 우려를 표했다. 미나는 \"대장은 건강검진할 때마다 용종을 계속 뗐다\"며 \"그래서 아침마다 당근, 양배추, 사과 이런 걸 먹으니까 오늘은 용종 안 낄 것 같다. 용종 떼는 날 과자 먹고 그랬다. 원래 그러면 안 되는데. 어쨌든 오늘 대장이 좋으면 섬유질이 효과가 있는 것\"이라고 말했다.\n\n그러나 미나는 대장내시경 이후 용종을 뗐다는 결과를 받았다. 집으로 돌아가며 미나는 \"여보랑 고기 뷔페 가고 맛 있는거 먹으려 했는데 또 용종을 하나 뗐더라. 2년에 한 번씩 건강검진을 할때마다 용종을 7개씩 뗐었다\"고 아쉬워했다. 류필립은 \"7개면 의사선생님도 당황하겠다\"고 웃었다.\n이에 미나는 \"(용종이) 암이 될 수도 있는 거다. 야채를 싫어했는데 지금은 아침마다 당근, 사과, 양배추 이런 걸 먹으니까 확실히 용종 숫자가 줄었다\"면서도 \"과자 먹는 숫자는 더 늘었다\"고 말해 웃음을 자아냈다. 류필립은 \"일곱 개에서 한 개로 줄었으면 거의 80%, 90% 감소다. 식단이 효과가 있는 것\"이라고 칭찬했다.\n\n미나는 \"나이 드니까 안 좋은 걸 먹으면 바로 몸에 나타난다. 진짜 그래서 운동하는 거다. 그나마 근력이 잘 생기는 체질이라 근육이 잘 버티고 있으니까 먹는 그대로 몸에 쌓이지 않아 그나마 날씬한 것\"이라며 \"그래서 사람들이 엄청 굶는다고 착각하시는데 식단은 60대 되면 살기 위해 할까 보다. 먹을 건 못 참는다\"고 털어놨다.\n\n이후 미나는 건강검진 결과를 확인하기 위해 다시 병원을 찾았다. 의사는 \"간 수치, 통풍, 췌장 수치, 염증 반응 수치가 전부 정상\"이라며 \"콜레스테롤이 약간 높지만 약을 먹을 단계는 아니다. 간 기능은 다 정상인데 당 수치가 약간 올랐다. 그냥 운동하시고 식단 조절만 하시면 된다\"고 설명했다.\n\n대장내시경에서 나온 용종에 대해서는 \"조직검사 결과 선종이 나왔다. 선종과 톱니모양 용종은 암이 될 수 있는 전암성 병변이라고 생각하면 된다\"며 \"한 개가 나왔다. 그러면 사실 4~6년 뒤에 하셔도 된다. 가공육 같은 것만 안 드시면 된다. 사실 대부분의 원인은 그냥 발",
      "content": "[마이데일리 = 강다윤 기자] 가수 미나(54·심민아)가 건강검진 결과를 공개했다.20일 유튜브 채널 'Feelme 필미커플'에는 '의사도 놀란 55세 가수 미나의 충격적인 건강검진 결과는 어땠길래..?'라는 제목의 영상이 업로드됐다.공개된 영상에서 미나는 새벽 5시 30분부터 건강검진 준비에 나섰다. 그는 \"2년 만에 위내시경이랑 대장내시경을 하기로 해서 대장약을 먹으려고 일어났다. 물 네 잔인데 너무 힘들다. 못 잘 것 같다\"고 토로했다.남편 류필립(37·박필립)이 운전하는 차를 타고 병원으로 향하던 미나는 \"40대 넘어서 건강검진을 받기 시작했다. 아빠가 내가 37, 38살 때 돌아가셨다. 그래서 건강검진을 시작했고, 2년 전에 엄마가 돌아가시니까 이제 내가 50대 중반이 되니 곧 내 차례라는 생각이 들더라\"고 털어놨다.이어 \"그저께 갑자기 심장이 찌릿찌릿한 것 같아 무서워서 병원에 가 심전도랑 심장 초음파까지 다 받았다. 그런데 너무 튼튼하다고 하더라. 심장으로 흐르는 피가 너무 깨끗하고 튼튼하다고 했다\"고 멋쩍게 웃었다.식단과 운동에 대한 솔직한 생각도 밝혔다. 미나는 \"안 좋은 음식을 많이 먹는다. 중국 활동할 때 기름진 걸 얼마나 많이 먹었겠나. 그땐 젊어서 운동도 잘 못 했다\"며 \"이제는 확실히 50대가 되니까 운동이 살길이다. 몸매 관리보다는 건강, 죽기 싫어서 운동하는 것\"이라고 말했다.그러면서 \"어제 하루 흰죽만 먹으면서 느낀 게 식단은 못 하겠다는 거다. 일단 많이 먹어야 한다. 그래도 못 먹는 여자보다 낫지 않냐\"고 너스레를 떨었다. 이를 들은 류필립은 \"잘 먹고 운동 잘하는 게 제일 좋다\"고 맞장구쳤다.병원에 도착한 미나는 혈압부터 쟀다. 107, 63이라과가 나온 가운데 그는 \"1년 전에 고지혈증 조심하라고 경과를 보자고 했고, 간종양 때문에 6개월 후 초음파, 복부 초음파도 6개월마다 하라고 했다. 그런데 6개월마다 못 왔다\"고 설명했다.류필립은 \"여보가 그게 많더라. 용종이 많아서\"라며 우려를 표했다. 미나는 \"대장은 건강검진할 때마다 용종을 계속 뗐다\"며 \"그래서 아침마다 당근, 양배추, 사과 이런 걸 먹으니까 오늘은 용종 안 낄 것 같다. 용종 떼는 날 과자 먹고 그랬다. 원래 그러면 안 되는데. 어쨌든 오늘 대장이 좋으면 섬유질이 효과가 있는 것\"이라고 말했다.그러나 미나는 대장내시경 이후 용종을 뗐다는 결과를 받았다. 집으로 돌아가며 미나는 \"여보랑 고기 뷔페 가고 맛 있는거 먹으려 했는데 또 용종을 하나 뗐더라. 2년에 한 번씩 건강검진을 할때마다 용종을 7개씩 뗐었다\"고 아쉬워했다. 류필립은 \"7개면 의사선생님도 당황하겠다\"고 웃었다.이에 미나는 \"(용종이) 암이 될 수도 있는 거다. 야채를 싫어했는데 지금은 아침마다 당근, 사과, 양배추 이런 걸 먹으니까 확실히 용종 숫자가 줄었다\"면서도 \"과자 먹는 숫자는 더 늘었다\"고 말해 웃음을 자아냈다. 류필립은 \"일곱 개에서 한 개로 줄었으면 거의 80%, 90% 감소다. 식단이 효과가 있는 것\"이라고 칭찬했다.미나는 \"나이 드니까 안 좋은 걸 먹으면 바로 몸에 나타난다. 진짜 그래서 운동하는 거다. 그나마 근력이 잘 생기는 체질이라 근육이 잘 버티고 있으니까 먹는 그대로 몸에 쌓이지 않아 그나마 날씬한 것\"이라며 \"그래서 사람들이 엄청 굶는다고 착각하시는데 식단은 60대 되면 살기 위해 할까 보다. 먹을 건 못 참는다\"고 털어놨다.이후 미나는 건강검진 결과를 확인하기 위해 다시 병원을 찾았다. 의사는 \"간 수치, 통풍, 췌장 수치, 염증 반응 수치가 전부 정상\"이라며 \"콜레스테롤이 약간 높지만 약을 먹을 단계는 아니다. 간 기능은 다 정상인데 당 수치가 약간 올랐다. 그냥 운동하시고 식단 조절만 하시면 된다\"고 설명했다.대장내시경에서 나온 용종에 대해서는 \"조직검사 결과 선종이 나왔다. 선종과 톱니모양 용종은 암이 될 수 있는 전암성 병변이라고 생각하면 된다\"며 \"한 개가 나왔다. 그러면 사실 4~6년 뒤에 하셔도 된다. 가공육 같은 것만 안 드시면 된다. 사실 대부분의 원인은 그냥 발생하는 것\"이라고 말했다.또 의사는 \"경동맥도 깨끗하고 갑상선 초음파에서도 크게 이상이 없다. 그 흔한 결절도 없고 엑스레이도 정상\"이라며 \"골밀도가 엄청 좋다. 20대 평균보다 높다. 검사 결과상 사실 큰 문제는 없다\"고 했다. 다만 식단 관리와 근력 운동은 꾸준히 할 것을 당부했다.집으로 돌아온 미나는 류필립과 나란히 앉아 결과지를 살펴봤다. 류필립이 \"놀라웠던 결과는 골밀도\"라고 짚자 미나는 \"예전에도 골밀도가 20대보다 훨씬 좋고 100세가 넘어도 절대 구부러지지 않는다고 했는데, 5년이 지나 걱정됐다. 그런데 아직도 20대보다 좋다더라\"고 기뻐했다.이어 미나는 \"아무래도 내가 잘 먹지 않나. 이것저것 잘 먹고 운동으로 근육을 만들어 놓으니까 뼈가 보호되는 것 같다\"며 \"식단이 좀 안 좋다. 아침은 좋은데 저녁마다 군것질을 너무 많이한다\"고 말했다. 그러면서 \"먹을 건 못 줄이더라도 집에서라도 운동하려고 헬스장을 마련했다\"고 실내자전거를 보여줘 웃음을 자아냈다.한편 미나와 류필립은 2018년 결혼했다. 최근에는 남양주에 위치한 테라스 4개 규모의 새 집을 공개해 화제를 모았다.많이 본 뉴스\"왜 아이유까지 끌어들여?\"…무차별 폭로 MC몽, 황당한 '물귀신 작전'에 비난 폭발[MD이슈]“이미지 세탁하나” 43억 횡령 황정음, “최고 유튜버 되겠다” 복귀에 싸늘[MD이슈]\"아이 있는 돌싱 원해\" 미혼 박혜경, 솔로 4년 차 '남친'이 꼭 필요한 이유? [물어보살]",
      "thumbnail_url": "https://img.mydaily.co.kr/photos/2026/05/21/2026052114003625829_l.jpg",
      "category": "K-pop",
      "priority": 2,
      "collected_at": "2026-05-21T06:30:39.571207",
      "status": "unreviewed",
      "evaluated_at": null,
      "score": null,
      "filter_reason": "K-pop 키워드: 아이유"
    },
    {
      "guid": "2026052113594716835",
      "source": "MyDaily_스타",
      "title": "최준용 \"스타벅스는 멸공커피\" VS 한정수 \"이제 가지 맙시다\" 탈벅 선언 [MD이슈]",
      "link": "https://www.mydaily.co.kr/page/view/2026052113594716835",
      "published": "2026-05-21T13:59:55+09:00",
      "summary": "[마이데일리 = 곽명동 기자]스타벅스코리아의 ‘탱크데이(Tank Day)’ 프로모션 논란이 사회적 파장을 일으키는 가운데, 배우 한정수가 공개 불매를 선언했다.\n\n\n한정수는 20일 개인 계정에 “이제 가지 맙시다”라는 짧은 글과 함께 잘린 스타벅스 카드 사진을 게재했다. 최근 온라인상에서 확산 중인 ‘탈벅(스타벅스 탈퇴)’ 움직임에 동참한 것으로 풀이된다. 그는 이를 조롱하는 일부 네티즌을 향해 “내가 너보다 (돈이) 없겠냐”, “응, 너” 등의 댓글을 달며 정면으로 응수했다.\n\n반면, 드라마 '야인시대'의 배우 최준용은 스타벅스 음료를 마시는 사진과 함께 \"커피는 스벅이지\"라는 글을 게재해 상반된 태도를 보였다. 해당 게시물에는 '#멸공형아', '#멸공커피', '#스타벅스' 등의 해시태그가 함께 달렸으며, 가수 김송이 ‘박수’ 이모티콘을 남기며 응원의 뜻을 보탰다.\n\n앞서 스타벅스는 지난 18일 '탱크 시리즈' 프로모션을 진행하며 홍보 이미지에 '탱크데이', '책상에 탁!' 등의 문구를 사용했다. 소비자들은 이것이 1980년 5·18 민주화운동 당시 계엄군의 탱크 진압과 1987년 박종철 열사 고문치사 사건 당시 공안 당국의 대표적 은폐 발언(“책상을 탁 치니 억 하고 죽었다”)을 연상시킨다며, 민주화운동을 조롱·폄훼한 것이 아니냐고 강하게 반발했다.\n\n이에 대해 이재명 대통령은 \"대한민국 공동체와 기본적 인권, 민주주의 가치를 부정하는 이런 저질 장사치의 비인간적 막장 행태에 분노한다\"며 \"마땅히 그에 상응하는 도덕적·행정적·법적·정치적 책임이 주어져야 할 것\"이라고 강조한 바 있다.",
      "content": "[마이데일리 = 곽명동 기자]스타벅스코리아의 ‘탱크데이(Tank Day)’ 프로모션 논란이 사회적 파장을 일으키는 가운데, 배우 한정수가 공개 불매를 선언했다.한정수는 20일 개인 계정에 “이제 가지 맙시다”라는 짧은 글과 함께 잘린 스타벅스 카드 사진을 게재했다. 최근 온라인상에서 확산 중인 ‘탈벅(스타벅스 탈퇴)’ 움직임에 동참한 것으로 풀이된다. 그는 이를 조롱하는 일부 네티즌을 향해 “내가 너보다 (돈이) 없겠냐”, “응, 너” 등의 댓글을 달며 정면으로 응수했다.반면, 드라마 '야인시대'의 배우 최준용은 스타벅스 음료를 마시는 사진과 함께 \"커피는 스벅이지\"라는 글을 게재해 상반된 태도를 보였다. 해당 게시물에는 '#멸공형아', '#멸공커피', '#스타벅스' 등의 해시태그가 함께 달렸으며, 가수 김송이 ‘박수’ 이모티콘을 남기며 응원의 뜻을 보탰다.앞서 스타벅스는 지난 18일 '탱크 시리즈' 프로모션을 진행하며 홍보 이미지에 '탱크데이', '책상에 탁!' 등의 문구를 사용했다. 소비자들은 이것이 1980년 5·18 민주화운동 당시 계엄군의 탱크 진압과 1987년 박종철 열사 고문치사 사건 당시 공안 당국의 대표적 은폐 발언(“책상을 탁 치니 억 하고 죽었다”)을 연상시킨다며, 민주화운동을 조롱·폄훼한 것이 아니냐고 강하게 반발했다.이에 대해 이재명 대통령은 \"대한민국 공동체와 기본적 인권, 민주주의 가치를 부정하는 이런 저질 장사치의 비인간적 막장 행태에 분노한다\"며 \"마땅히 그에 상응하는 도덕적·행정적·법적·정치적 책임이 주어져야 할 것\"이라고 강조한 바 있다.많이 본 뉴스\"왜 아이유까지 끌어들여?\"…무차별 폭로 MC몽, 황당한 '물귀신 작전'에 비난 폭발[MD이슈]“이미지 세탁하나” 43억 횡령 황정음, “최고 유튜버 되겠다” 복귀에 싸늘[MD이슈]\"아이 있는 돌싱 원해\" 미혼 박혜경, 솔로 4년 차 '남친'이 꼭 필요한 이유? [물어보살]",
      "thumbnail_url": "https://img.mydaily.co.kr/photos/2026/05/21/2026052113575437866_l.jpg",
      "category": "K-pop",
      "priority": 2,
      "collected_at": "2026-05-21T06:30:39.571999",
      "status": "unreviewed",
      "evaluated_at": null,
      "score": null,
      "filter_reason": "K-pop 키워드: 아이유"
    },
    {
      "guid": "2026052113303247264",
      "source": "MyDaily_스타",
      "title": "\"유난 육아 논란\" 아야네, \"둘째 임신했는데 살 쭉쭉 빠져\" 근황",
      "link": "https://www.mydaily.co.kr/page/view/2026052113303247264",
      "published": "2026-05-21T13:30:49+09:00",
      "summary": "[마이데일리 = 곽명동 기자]뮤지컬 배우 이지훈의 아내 아야네가 최근 논란 이후 근황을 전했다.\n\n아야네는 21일 개인 소셜미디어(SNS) 계정에 \"살이 쭉쭉 빠져서 임신 초반 몸무게보다 -2kg\"라며 \"원래 없던 식탐이 생기다가 없어지다가 한다. 하루하루 다른 자아를 발견하는 중\"이라는 글을 게재했다.\n\n앞서 아야네는 최근 딸 루희의 어린이집 가방에서 사탕 껍질을 발견했다며 아쉬움을 토로해 화제를 모은 바 있다.\n\n당시 그는 \"루희는 아직 무염식을 하는 아기라 과자도 떡뻥만 먹고 비타민 사탕도 안 먹였다. 그런데 어제 어린이집에서 가져온 가방에서 사탕 껍질을 발견했다\"면서 \"그동안은 '이거 못 먹는 거야'라고 설득해 왔는데, 이제 맛을 알게 되어버렸다\"고 답답함을 호소했다.\n\n해당 발언이 온라인상에서 '어린이집을 향한 과도한 저격이 아니냐'는 논란으로 확산되자, 남편 이지훈은 SNS를 통해 \"우리 루희는 무염(식) 중이다. 유난 떨어 미안하다\"고 직접 진화에 나서기도 했다.\n\n한편 이지훈과 아야네는 지난 2021년 결혼해 2024년 시험관 시술을 거쳐 첫째 딸 루희를 품에 안았다. 최근에는 둘째 임신 소식을 전해 많은 축하를 받았다.",
      "content": "[마이데일리 = 곽명동 기자]뮤지컬 배우 이지훈의 아내 아야네가 최근 논란 이후 근황을 전했다.아야네는 21일 개인 소셜미디어(SNS) 계정에 \"살이 쭉쭉 빠져서 임신 초반 몸무게보다 -2kg\"라며 \"원래 없던 식탐이 생기다가 없어지다가 한다. 하루하루 다른 자아를 발견하는 중\"이라는 글을 게재했다.앞서 아야네는 최근 딸 루희의 어린이집 가방에서 사탕 껍질을 발견했다며 아쉬움을 토로해 화제를 모은 바 있다.당시 그는 \"루희는 아직 무염식을 하는 아기라 과자도 떡뻥만 먹고 비타민 사탕도 안 먹였다. 그런데 어제 어린이집에서 가져온 가방에서 사탕 껍질을 발견했다\"면서 \"그동안은 '이거 못 먹는 거야'라고 설득해 왔는데, 이제 맛을 알게 되어버렸다\"고 답답함을 호소했다.해당 발언이 온라인상에서 '어린이집을 향한 과도한 저격이 아니냐'는 논란으로 확산되자, 남편 이지훈은 SNS를 통해 \"우리 루희는 무염(식) 중이다. 유난 떨어 미안하다\"고 직접 진화에 나서기도 했다.한편 이지훈과 아야네는 지난 2021년 결혼해 2024년 시험관 시술을 거쳐 첫째 딸 루희를 품에 안았다. 최근에는 둘째 임신 소식을 전해 많은 축하를 받았다.많이 본 뉴스\"왜 아이유까지 끌어들여?\"…무차별 폭로 MC몽, 황당한 '물귀신 작전'에 비난 폭발[MD이슈]“이미지 세탁하나” 43억 횡령 황정음, “최고 유튜버 되겠다” 복귀에 싸늘[MD이슈]\"아이 있는 돌싱 원해\" 미혼 박혜경, 솔로 4년 차 '남친'이 꼭 필요한 이유? [물어보살]",
      "thumbnail_url": "https://img.mydaily.co.kr/photos/2026/05/21/2026052113300698538_l.jpg",
      "category": "K-pop",
      "priority": 2,
      "collected_at": "2026-05-21T06:30:39.572804",
      "status": "unreviewed",
      "evaluated_at": null,
      "score": null,
      "filter_reason": "K-pop 키워드: 아이유"
    },
    {
      "guid": "https://tvreport.co.kr/uncategorized/article/1046748/",
      "source": "TVReport",
      "title": "김요한, ‘6세 연하’ 이주연과 핑크빛→관계 재정의…”우리 무슨 사이냐” (‘신랑수업2’)",
      "link": "https://tvreport.co.kr/entertainment/article/1046748/",
      "published": "2026-05-21T06:22:05+00:00",
      "summary": "[TV리포트=윤희정 기자] 배구 선수 출신 방송인 김요한이 6세 연하 운동 센터 CEO 이주연과 대구 당일치기 여행을 떠난다. 21일 방송되는 채널A ‘신랑수업2’에서는 ‘요주의 커플’ 김요한X이주연이 대구에서 알찬 데이트 코스를 즐기며 급속도로 가까워지는 모습이 펼쳐",
      "content": "[TV리포트=윤희정 기자]배구 선수 출신 방송인 김요한이 6세 연하 운동 센터 CEO 이주연과 대구 당일치기 여행을 떠난다.21일 방송되는 채널A ‘신랑수업2’에서는 ‘요주의 커플’ 김요한X이주연이 대구에서 알찬 데이트 코스를 즐기며 급속도로 가까워지는 모습이 펼쳐진다. 이날 두 사람은 기차만큼 빠른 ‘초고속 연애’의 본격적인 시동을 건다는 후문이다.아침 일찍 서울역에서 만난 김요한과 이주연은 “데이트로 기차 여행을 해본 적은 처음”이라고 입을 모으며 설레는 마음을 드러낸다. 두 사람은 열차 안에서 간질간질한 ‘ASMR 대화’를 나누고, 나란히 단잠에 빠진다. 잠시 후, 대구에 도착한 김요한은 “대구행 티켓은 끊었지만, 돌아오는 티켓은 아직 구입하지 않았다”라고 너스레를 떨어 분위기를 뜨겁게 달군다.김요한이 야심 차게 준비한 대구 데이트 첫 코스는 이주연이 가보고 싶다고 했던 동물원. 두 사람은 귀여운 동물들에게 먹이를 주며 밀착 스킨십까지 선보여 눈길을 끈다. 이어 대구의 중심인 동성로에서 길거리 데이트를 하고 놀이동산도 방문하는데, 이를 지켜보던 ‘연애 부장’ 송해나는 “일정이 너무 빡빡하다, 데이트가 아니라 전지훈련 같다”라고 우려해 ‘짠내’ 웃음을 자아낸다.그런가 하면, 저녁 식사 자리에서 김요한은 이주연에게 진지한 대화를 시도한다. 그는 “이제 존칭은 그만 썼으면 좋겠다. 존칭은 아무래도 거리감이 있지 않냐”라고 말한다.그러면서 김요한은 “여기서 궁금해지는 게, 우리는 무슨 사이인 건지?”라며 이주연을 지그시 바라본다.이주연 역시 “사실 주변에서 남자 친구가 있는지를 물어볼 때마다 대답하기가 애매하긴 했다”라며, “저랑 어떤 사이라고 생각하시냐?”라고 반문해 모두를 놀라게 한다.과연 김요한이 이주연과의 관계를 스스로 어떻게 정의 내릴지, 두 사람의 설레는 대구 데이트는 21일 밤 10시 방송되는 채널A ‘신랑수업2’에서 만날 수 있다.윤희정 기자 / 사진 = 채널A ‘신랑수업2’",
      "thumbnail_url": "https://img.tvreportcdn.de/cms-content/uploads/2026/05/21/bd821782-84bc-4fa0-a70e-64d1e2c349d8.jpg",
      "category": "K-pop",
      "priority": 2,
      "collected_at": "2026-05-21T06:30:41.788838",
      "status": "unreviewed",
      "evaluated_at": null,
      "score": null,
      "filter_reason": "K-pop 키워드: 있지"
    },
    {
      "guid": "https://tvreport.co.kr/uncategorized/article/1046744/",
      "source": "TVReport",
      "title": "“지분 얼마나 줄까”…문원, ♥신지와 함께한 곡 작업 비하인드 공개 [RE:뷰]",
      "link": "https://tvreport.co.kr/entertainment/article/1046744/",
      "published": "2026-05-21T06:18:22+00:00",
      "summary": "[TV리포트=민세윤 기자] 가수 신지와 결혼한 문원이 결혼 후 급격히 떨어진 체력을 고백하며, 아내 신지와 함께한 특별한 곡 작업 비하인드 스토리를 공개했다. 지난 20일 채널 '어떠신지?!?'에는 결혼식을 마친 후 함께 미용실을 찾은 신지와 문원의 알콩달콩한 신혼 일",
      "content": "[TV리포트=민세윤 기자] 가수 신지와 결혼한 문원이 결혼 후 급격히 떨어진 체력을 고백하며, 아내 신지와 함께한 특별한 곡 작업 비하인드 스토리를 공개했다.지난 20일 채널 ‘어떠신지?!?’에는 결혼식을 마친 후 함께 미용실을 찾은 신지와 문원의 알콩달콩한 신혼 일상이 공개됐다. 이날 영상에서 문원은 결혼 준비로 인해 달라진 자신의 신체 변화를 솔직하게 언급했다. 그는 “결혼식 후 체력이 너무 달린다”며 앞서 두 달간 14kg을 감량하며 근육과 살을 한꺼번에 뺀 탓에 찾아온 무력감을 고백하며 운동의 필요성을 강조했다.화제는 자연스럽게 두 사람이 함께 작업한 신곡 이야기로 이어졌다. 문원은 이번 신곡에 대해 “사랑하는 여자에게 고백조차 못 하는 남자의 찌질한 짝사랑을 담은 노래”라고 소개했다. 특히 아내 신지가 직접 곡 작업에 깊이 관여했음을 밝혀 눈길을 끌었다. 문원은 “아내에게 가사와 노래를 들려주며 의견을 물었고, 특정 구간을 수정하는 등 함께 참여했다”고 전했다.이어 신지의 기여도를 떠올리며 “와이프 지분을 얼마나 줄지 지금 고민 중”이라고 너스레를 떨어 웃음을 자아냈다.결혼식 직후 체력 저하라는 현실적인 신혼의 고충을 겪고 있지만, 꿈을 위해 기꺼이 곡을 쓰고 지분까지 고민하는 문원의 사랑꾼 면모는 많은 이들의 부러움을 샀다.지난달 2일 결혼에 골인해 새로운 출발을 알린 두 사람의 앞날에 팬들의 응원이 쏟아지고 있다.누리꾼들은 ‘신지랑 문원 님 같이 곡 작업이라니 너무 로맨틱하다’, ‘결혼 준비하면서 14kg이나 뺐다니 체력이 달릴 만도 하네’, ‘지분 고민한다는 게 왜 이렇게 귀엽지’, ‘두 분 음악적으로도 서로 배려하는 모습 보기 좋다’ 등의 반응을 보였다.민세윤 기자 / 사진=신지, 채널 ‘어떠신지?!?’",
      "thumbnail_url": "https://img.tvreportcdn.de/cms-content/uploads/2026/05/21/b752e0c4-8581-4c1e-88cf-6a96e275d254.jpg",
      "category": "K-pop",
      "priority": 2,
      "collected_at": "2026-05-21T06:30:41.791826",
      "status": "unreviewed",
      "evaluated_at": null,
      "score": null,
      "filter_reason": "K-pop 키워드: 있지"
    },
    {
      "guid": "https://tvreport.co.kr/uncategorized/article/1046742/",
      "source": "TVReport",
      "title": "이하늘, ‘마약·성범죄’ 허위 사실 유포 혐의로 법원行…6월 재판",
      "link": "https://tvreport.co.kr/entertainment/article/1046742/",
      "published": "2026-05-21T06:15:52+00:00",
      "summary": "[TV리포트=최민준 기자] 그룹 'DJ DOC' 멤버 이하늘(본명 이근배)이 동료 연예인 등과의 법적 공방 끝에 결국 정식 재판을 받게 됐다. 주비트레인 소속사 베이스캠프스튜디오는 21일 TV리포트에 이하늘이 정보통신망법상 명예훼손 및 모욕 등의 혐의로 오는 6월 12",
      "content": "[TV리포트=최민준 기자] 그룹 ‘DJ DOC’ 멤버 이하늘(본명 이근배)이 동료 연예인 등과의 법적 공방 끝에 결국 정식 재판을 받게 됐다.주비트레인 소속사 베이스캠프스튜디오는 21일 TV리포트에 이하늘이 정보통신망법상 명예훼손 및 모욕 등의 혐의로 오는 6월 12일 정식 재판을 앞두고 있다고 전했다. 이번 재판은 가수 주비트레인과 연예 기획사 이모 대표를 상대로 한 허위사실 유포 및 모욕 혐의에 따른 것으로 전해졌다.앞서 이하늘은 이들을 상대로 마약 투약, 미성년자 성범죄, 사기 및 횡령 등의 의혹을 제기해 소송에 휘말렸다. 이 과정에서 의정부지방검찰청 고양지청은 올 초인 1월 22일 이하늘에게 모욕 혐의를 적용해 벌금 200만 원의 구약식 처분을 내린 바 있다. 구약식은 정식 재판 없이 벌금형을 내리는 절차이나 이번 사건은 최종적으로 법원의 정식 재판 절차를 밟게 됐다.양측의 갈등은 수년 전부터 지속되어 왔다. 이하늘 측은 주비트레인과 이 대표를 상대로 사기 및 횡령 혐의 등으로 맞고소를 진행하기도 했으나 검찰은 이에 대해 무혐의 처분을 내렸다. 반면 주비트레인 측은 소속사와의 노동 분쟁 관련 기관인 노동위원회 등에서 승소 판결을 받았음을 근거로 이하늘의 주장이 근거 없는 허위사실이라는 입장이다.현재 이번 사건 외에도 양측 사이에는 명예훼손과 모욕 혐의 등으로 얽힌 추가 고소 건들이 여러 건 진행 중인 것으로 알려졌다. 아울러 베이스캠프스튜디오에 따르면 이하늘의 소속사 관계자들과 주변 인물들 역시 무고 및 개인정보보호법 위반 혐의 등으로 검찰에 송치되거나 수사 선상에 오른 상태다.법적 공방이 이어지는 가운데 이하늘은 최근 요식업에 뛰어들어 자영업자로서의 행보를 이어가고 있으나 이 과정에서도 잡음이 끊이지 않고 있다. 그가 운영 중인 곱창집은 지난 2월 팬미팅 진행 도중 식품위생법 위반 신고를 당한 데 이어, 최근 16일에는 매장 내 디제잉 방송 중 소음 민원으로 경찰이 출동하는 소동을 겪었다. 이에 대해 이하늘은 개인 계정 라이브를 통해 억울함과 분노를 표출함과 동시에, 영업정지 등 온라인상에 유포된 일부 루머에 대해서는 명백한 허위사실이라며 법적 대응을 예고하기도 했다.최민준 기자 / 사진= TV리포트 DB",
      "thumbnail_url": "https://img.tvreportcdn.de/cms-content/uploads/2026/05/21/2efa201d-83b0-4a4f-8565-cdefa2bb5856.jpg",
      "category": "K-pop",
      "priority": 2,
      "collected_at": "2026-05-21T06:30:41.793188",
      "status": "unreviewed",
      "evaluated_at": null,
      "score": null,
      "filter_reason": "K-pop 키워드: 팬미팅"
    },
    {
      "guid": "https://tvreport.co.kr/uncategorized/article/1046736/",
      "source": "TVReport",
      "title": "“연상호, 러브, 좀비”…진화하는 ‘군체’와 멈춰있는 인간 [씨네:리포트]",
      "link": "https://tvreport.co.kr/uncategorized/article/1046736/",
      "published": "2026-05-21T05:40:02+00:00",
      "summary": "[TV리포트=강지호 기자] 약은 약사에게, 좀비는 연상호에게. 단순히 새로운 좀비를 보여주는 작품이 아니다. 개인과 집단, 연결과 고립, 그리고 현대 사회의 불안을 장르적 언어로 풀어낸 영화 '군체(연상호 감독·㈜쇼박스)'다. 제79회 칸 영화제를 찾은 '군체'는 21",
      "content": "[TV리포트=강지호 기자] 약은 약사에게, 좀비는 연상호에게. 단순히 새로운 좀비를 보여주는 작품이 아니다. 개인과 집단, 연결과 고립, 그리고 현대 사회의 불안을 장르적 언어로 풀어낸 영화 ‘군체(연상호 감독·㈜쇼박스)’다.제79회 칸 영화제를 찾은 ‘군체’는 21일 국내 개봉했다. 영화 ‘부산행’으로 한국형 좀비물의 새 흐름을 만든 연상호 감독이 ‘반도’ 이후 6년 만에 들고 온 좀비 장르다.연 감독이 좀비를 얼마나 집요하게 탐구해 왔는지를 다시금 증명한 영화 ‘군체’는 정체불명의 감염 사태로 봉쇄된 건물 안, 고립된 생존자들이 예측할 수 없는 형태로 진화하는 감염자들에 맞서는 내용을 담은 작품이다.11년 만에 스크린 복귀에 나선 전지현은 생명공학 박사 권세정 역으로 극의 중심을 잡는다. 연상호의 페르소나 구교환은 천재 생물학자이자 감염 사태의 시작이 된 서영철 역을 맡았다.이 밖에도 영화의 배경이 되는 둥우리 빌딩의 보안팀 직원 최현석 역의 지창욱, 현석의 누나이자 하반신 마비로 휠체어를 사용하는 최현희 역의 김신록, 생명공학자로 권세정의 전 남편인 한규성 역의 고수, 그의 아내 공설희 역의 신현빈 등 믿고 보는 배우들이 ‘군체’를 위해 뭉쳤다.▲ 감염의 시작부터 진화의 끝까지…새로운 종(種)의 탄생시작부터 강렬하다. 서영철의 테러 예고로 막을 연 ‘군체’는 첫 감염자(좀비)의 등장부터 “역시 좀비는 연상호”라는 감탄을 절로 끌어낸다.사지가 비현실적으로 뒤틀리고 꺾이는 움직임, 뼈가 갈리는 듯한 효과음, 그리고 피 대신 하얀 점액질을 토해내며 탄생하는 감염자들의 모습은 기존 좀비물과 결이 다르다. 이들은 단순한 좀비가 아니라 ‘새로운 종’처럼 그려진다.기존의 좀비가 피로 얼룩져 이미 죽어버린 언데드(undead) 상태로 인식되는 경우가 일반적이었다면, ‘군체’ 속 좀비는 감염 상태로 ‘치료가 필요한 환자’로 표현된다.둥우리 빌딩 내부의 상황은 다르지만, 정부는 이들을 사살 가능한 존재로 보고 있지 않기 때문에 내부 인원들의 목표 역시 ‘좀비를 죽이고 살아남기’가 아니라 ‘빌딩을 빠져나가는 것’으로 설정된다. 영화 속 배경이 빌딩 안으로 통제됐기 때문에 가능한 플롯이다.이 과정에서 자신을 ‘백신’이라 주장하는 테러리스트 서영철의 존재가 극에 흥미로운 변주를 더한다. 모든 사태의 원인이지만, 동시에 생존을 위해 반드시 필요한 존재라는 점에서 그는 단순한 빌런 이상의 역할을 수행한다. 내부 인원들은 생존을 위해서 ‘인간 백신’ 서영철을 찾아내야 한다.무엇보다 ‘군체’의 가장 큰 차별점은 감염자들이 끊임없이 진화한다는 점이다. 이들은 기괴한 하울링과 함께 정보를 공유하고, 집단 지성을 형성하며 점점 더 빠르게 ‘업데이트’된다. 네발로 기어다니던 감염자들은 어느 순간 직립 보행을 시작하고, 종국에는 글자를 검색하는 단계까지 도달한다.그 중심에는 서영철이 있다. 감염자들의 신처럼 묘사되는 그는 빌딩 곳곳을 자유롭게 오가며 생존자들을 비웃는다. 영화 속 감염자들은 마치 그의 지휘 아래 움직이는 오케스트라처럼 보인다. 그리고 그들의 움직임은 점차 서영철 개인의 의지를 집단화한 군대처럼 변해간다.같은 플롯이 반복되는 구조는 호불호가 갈릴 수 있다. 서영철이 주인공 일행에게 붙잡히고 빠져나가는 흐름이 큰 틀이 되기 때문. 하지만 이 단순한 구조 덕분에 관객은 감염자들의 변화와 진화를 훨씬 직관적으로 받아들이게 된다.▲ 새로운 것은 좀비뿐…진화하는 감염체와 멈춰있는 인간‘군체’의 주인공은 인간이 아니라 좀비다. 새로운 것도 좀비뿐이다.영화는 감염자들의 설정과 진화 과정에는 놀라울 정도로 공을 들였지만, 정작 인물들은 지나치게 평면적이다. 관계성과 캐릭터는 색다를지 몰라도, 정작 서사는 움직이지 못했다.물론 재난 장르에서 이기적이고 답답한 인간 군상은 필연적이다. 그런데 ‘군체’는 이 틀이 너무 단편적이다. 보편적이고 현실적이라고 하기에는 관객의 피로감을 유발하기 위한 장치처럼 느껴질 때가 많다.무음 모드가 없는 듯한 휴대전화, 위험 상황에서도 경고를 무시하는 행동 등, 영화는 인물의 선악을 지나치게 빠른 속도로 규정한다. 큰 반전도 없다. 감염자들의 설정과 움직임에 비해 캐릭터들의 서사는 지나치게 기능적으로 소비된다.서사가 불친절하니 이해하려면 머리를 써야 한다. 그런데 좀비의 진화를 따라가다 보면 인물들의 이야기에 귀를 기울일 시간이 없다. 초중반부는 감염과 관련된 세계관만으로도 흥미진진하고 몰입감도 높다. 이해를 위한 과정도 즐겁다.하지만 후반부로 갈수록 진화체들은 결국 서영철 한 사람의 의지로 움직이는 군단처럼 보인다. 러닝타임 내내 달려온 진화체의 마무리는 꽤 허무하고, 스케일 키우기 바쁜 영화는 인물의 이야기는 들려줄 생각이 없다. 그래서 결국 끝까지 캐릭터들과는 친해지지 못했다.이처럼 ‘군체’에서는 인간보다 좀비가 더 입체적이다. 기존 좀비 영화들이 인물 서사를 중심에 두고 좀비를 장치로 활용했다면, ‘군체’는 오히려 사람이 연 감독의 ‘좀비 사랑’ 세계관을 위한 도구처럼 느껴지기도 한다.▲ 집단 지성과 개별성…연상호가 던지는 흥미로운 질문그럼에도 ‘군체’가 매력적인 이유는 단순히 새로운 좀비 때문만은 아니다.연 감독은 이번 작품을 통해 집단 지성과 인간의 개별성에 대한 질문을 던진다. 영화 속 감염자들은 빠른 정보 공유를 통해 하나의 거대한 집단으로 연결된다. 그러나 그 집단은 결국 진정한 소통은 하지 못한다.잘못된 정보마저 빠르게 공유되며 전체의 오류를 만들어내고, 그 모습은 끝없이 원을 돌다 집단 폐사하는 개미 현상 ‘앤트밀’ 같은 형태로 이어진다.반면 권세정과 공설희가 보여주는 인간의 연대는 다르다. 완벽하지 않기에 조심스럽지만, 이해와 공감을 바탕으로 같은 목표를 향해 달려간다. 의지의 영역이다.서영철이 끊임없이 ‘소통’을 이야기하는 것도 인상적다. 그는 인간의 불완전한 소통이 비극을 만든다고 믿고, 완벽하게 연결된 ‘신인류’를 탄생시킨 것이라 말한다.하지만 아이러니하게도 누구보다 연결을 갈망했던 그는 끝내 가장 외로운 인물처럼 보인다. 감염자들의 하울링조차 결국 세상과 연결되고 싶었던 서영철의 절규로 들린다.영화가 가진 매력은 분명하다.하얀 점액질로 표현된 색다른 감염체, 현대무용수들이 참여해 만들어낸 기괴하면서도 아름다운 움직임, 끊임없이 진화하는 좀비들의 비주얼은 극장의 큰 스크린에서 압도적인 몰입감을 선사한다.특히 감염이 우연한 사고나 변이로 시작된 것이 아니라 의도적으로 만들어진 것이라는 설정 역시 현실적인 공포를 자극한다.전지현의 절제된 액션과 관객의 시선을 끌고 가는 안정적인 중심축 역할도 인상적이다. 지창욱과 김신록 남매의 서사는 다소 신파적이지만, 몇 안 되는 인간적인 감정을 남기는 장면으로 작동한다.‘군체’는 호불호가 있을 작품이다. 캐릭터성과 촘촘한 서사를 중요하게 여기는 관객이라면 아쉬움이 남을 수 있다. 반면 전에 없던 좀비와, 장르물의 몰입감을 경험하고 싶은 관객이라면 충분히 흥미롭게 즐길 수 있다. 빠른 전개만 기대했다면 설정을 따라가는 과정은 조금 버겁게 느껴질 수도.무엇보다 열린 결말로 끝나는 만큼 이후 이야기에 대한 궁금증도 남는다. 다양한 해석의 여지를 남기는 주제 의식 역시 인상적이다. 짜증을 유발하는 순간도 분명 있지만, 끝내 눈을 뗄 수 없게 만드는 힘이 있다. 그리고 영화를 보고 나면 자연스럽게 이런 생각이 남는다. 역시 좀비는 연상호다.5월 21일 개봉. 러닝타임 122분. 15세 이상 관람가마지막 한마디. 연 감독님, 구교환 아역 배우는 대체 어디서 찾으신 건가요(P)강지호 기자/ 사진= 영화 ‘군체’",
      "thumbnail_url": "https://img.tvreportcdn.de/cms-content/uploads/2026/05/21/7a0e0d22-e1bb-4184-8b6d-3df12e0dbe07.jpg",
      "category": "K-pop",
      "priority": 2,
      "collected_at": "2026-05-21T06:30:41.801066",
      "status": "unreviewed",
      "evaluated_at": null,
      "score": null,
      "filter_reason": "K-pop 키워드: 있지"
    },
    {
      "guid": "https://tvreport.co.kr/uncategorized/article/1046728/",
      "source": "TVReport",
      "title": "김종민, 스벅 ‘탱크데이’ 논란 속 5.18 의미 되짚는다…”잊지 말아야 할 역사” (‘사기꾼들’)",
      "link": "https://tvreport.co.kr/broadcast/article/1046728/",
      "published": "2026-05-21T05:28:58+00:00",
      "summary": "[TV리포트=윤희정 기자] ‘강연배틀쇼 사(史)기꾼들’이 5·18 민주화 운동을 기리기 위한 ‘다크 투어’ 강연을 예고했다. 21일 방송되는 JTBC ‘강연배틀쇼 사기꾼들’에서는 최태성이 역사적 사건인 5·18을 주제로 강연을 진행한다. 최태성은 \"이번 강연 준비가 그",
      "content": "[TV리포트=윤희정 기자] ‘강연배틀쇼 사(史)기꾼들’이 5·18 민주화 운동을 기리기 위한 ‘다크 투어’ 강연을 예고했다.21일 방송되는 JTBC ‘강연배틀쇼 사기꾼들’에서는 최태성이 역사적 사건인 5·18을 주제로 강연을 진행한다.최태성은 “이번 강연 준비가 그 어느 때보다 힘들었다”라고 밝히며, 강연 직전 손발이 떨릴 정도로 긴장한 모습을 보인다. 이번 방구석 역사 여행의 목적지는 5·18 민주화 운동이 있던 광주로, 최태성은 46주년을 맞은 이 운동의 의미를 되새기고 우리가 잊지 말아야 할 교훈을 전달할 예정이다.강연이 시작되자, 최태성은 1980년 5월 광주의 현장처럼 생생한 스토리텔링을 선보인다. 강연이 진행됨에 따라 참혹한 현실이 드러나고, 스튜디오는 충격과 분노로 가득 차게 된다.MC 김종민 역시 탄식하며 감정을 주체하지 못하고, ‘사심단’은 눈물을 흘리게 된다.이날 강연은 민주주의를 외치며 희생한 이들의 용기가 오늘날 우리에게 어떤 의미를 주는지를 탐구하는 시간을 제공한다.과연 최태성의 ‘광주 다크 투어’가 경쟁자 설민석의 ‘김구 로드’를 상대로 우승을 차지할지 귀추가 주목된다. 방송 후 긴급 대책 회의가 소집됐다는 이야기까지 전해지는 가운데 치열한 강연 배틀의 결과는 21일 저녁 8시 50분 JTBC ‘강연배틀쇼 사(史)기꾼들’에서 확인할 수 있다.올해 5·18 민주화 운동이 48주년을 맞은 가운데 스타벅스 코리아는 자사 애플리케이션을 통해 일명 ‘탱크데이’ 이벤트를 진행, ‘책상을 탁’ 등의 홍보 문구를 사용해 논란에 휩싸였다.해당 문구가 계엄군의 탱크 진입, 1987년 박종철 고문치사 사건을 떠올리게 한다는 것. 이후 대중들 사이에선 스타벅스 불매 운동을 하는 등 비난이 쏟아졌고, 정용진 회장은 “있어서도 안 되고 용납될 수도 없는 부적절한 마케팅”이라고 사과했다.윤희정 기자 / 사진 = TV리포트 DB, JTBC ‘강연배틀쇼 사(史)기꾼들’",
      "thumbnail_url": "https://img.tvreportcdn.de/cms-content/uploads/2026/05/21/56a56db5-91b4-4653-b53a-7018f987b576.jpg",
      "category": "K-pop",
      "priority": 2,
      "collected_at": "2026-05-21T06:30:41.807093",
      "status": "unreviewed",
      "evaluated_at": null,
      "score": null,
      "filter_reason": "K-pop 키워드: 투어"
    },
    {
      "guid": "https://tvreport.co.kr/uncategorized/article/1046718/",
      "source": "TVReport",
      "title": "공승연 분량, 20분에 그쳤다…역사 왜곡 논란 ‘대군부인’ 언급 전면 삭제 (‘유퀴즈’)",
      "link": "https://tvreport.co.kr/entertainment/article/1046718/",
      "published": "2026-05-21T05:02:18+00:00",
      "summary": "[TV리포트=김진수 기자] 배우 공승연이 tvN '유 퀴즈 온 더 블럭'에 출연해 솔직한 입담을 펼쳤지만, 최근 역사 왜곡 논란에 휩싸인 드라마 '21세기 대군부인'과 관련된 내용은 본 방송에서 모두 편집됐다. 지난 21일 방송된 '유 퀴즈 온 더 블럭'에는 데뷔 15",
      "content": "[TV리포트=김진수 기자] 배우 공승연이 tvN ‘유 퀴즈 온 더 블럭’에 출연해 솔직한 입담을 펼쳤지만, 최근 역사 왜곡 논란에 휩싸인 드라마 ’21세기 대군부인’과 관련된 내용은 본 방송에서 모두 편집됐다.지난 21일 방송된 ‘유 퀴즈 온 더 블럭’에는 데뷔 15년 만에 전성기를 맞은 공승연이 게스트로 출연했다. 이날 그는 SM엔터테인먼트 연습생으로 7년을 보냈던 시절부터 배우로 전향한 이후의 고충, 그리고 친동생인 트와이스 정연을 향한 애틋한 마음까지 진솔하게 털어놓으며 시청자들의 공감을 자아냈다.다만 최근 출연작인 MBC ’21세기 대군부인’은 방송 내내 전혀 찾아볼 수 없었다. 앞서 공개된 예고 영상에서는 유재석이 공승연을 소개하며 “’21세기 대군부인’으로 15년 만에 전성기를 맞이했다”고 언급했다. 공승연 역시 “아이유 씨, 변우석 씨 열차에 저도 탑승해 보겠다”고 말하며 작품에 대한 기대와 설렘을 드러냈다.기대와 다르게 정작 본 방송에서는 해당 장면이 모두 삭제됐다. 유재석은 단순히 “데뷔 15년 만에 전성기를 맞이한 배우”라고만 소개했고, 작품명은 끝내 언급되지 않았다.자막도 달라졌다. 예고편에 등장했던 “’21세기 대군부인’으로 15년 만에 전성기를 맞이한 공승연”이라는 표현 대신, 본 방송에서는 “15년 만에 연기력을 인정받은 배우 공승연의 이야기”라는 문구가 사용됐다.공승연은 ’21세기 대군부인’에서 윤이랑 역을 맡아 안정적인 연기를 선보이며 호평을 받았다. 작품을 통해 다시 주목받으며 ‘유 퀴즈 온 더 블럭’ 출연까지 성사된 것으로 보였지만, 작품이 최근 논란에 휩싸이면서 방송에서도 관련 내용이 전면 삭제된 것으로 해석된다.실제로 이날 공승연의 방송 분량은 약 20분가량으로, 같은 회차에 출연한 배우 유승목과 가수 비가 각각 30분 안팎의 분량을 차지한 것과 비교하면 다소 짧았다.’21세기 대군부인’은 높은 화제성과 시청률 속에 종영했지만, 지난 15일 방송된 11회가 논란의 중심에 섰다. 극 중 이안대군 역의 변우석이 대한제국 황제가 착용해야 할 십이면류관이 아닌 중국 제후국 군주가 쓰는 구류면류관을 착용한 채 등장했고, 신하들이 황제를 향해 “천세”를 외치는 장면이 방송되면서 역사 고증 오류 지적이 쏟아졌다.방송 직후 팬들은 “연기력을 보면 서브가 아니라 주연을 맡아도 전혀 손색없는 배우다”, “오랜 시간 끝에 빛을 보는 것 같아 응원했는데 작품 논란이 불거져 아쉽다”, “연기를 정말 안정감 있게 잘하더라. 앞으로가 더욱 기대된다” 등의 반응을 보이며 공승연에게 응원의 메시지를 전했다.tvN 예능 ‘유 퀴즈 온 더 블럭’은 매주 수요일 밤 8시 45분 방송된다.김진수 기자 / 사진 = TV리포트 DB, tvN ‘유 퀴즈 온 더 블럭’",
      "thumbnail_url": "https://img.tvreportcdn.de/cms-content/uploads/2026/05/21/fb6035d5-0fa3-41a7-abd9-0f7cc9b89ae1.jpg",
      "category": "K-pop",
      "priority": 2,
      "collected_at": "2026-05-21T06:30:41.814713",
      "status": "unreviewed",
      "evaluated_at": null,
      "score": null,
      "filter_reason": "K-pop 키워드: 트와이스, 아이유, 데뷔, SM엔터"
    },
    {
      "guid": "https://tvreport.co.kr/uncategorized/article/1046712/",
      "source": "TVReport",
      "title": "배우 김지연, 과거 전남친 때문에 10억 빚 떠안아→보험 설계사로 ‘인생 2막’ (‘같이 삽시다’)",
      "link": "https://tvreport.co.kr/broadcast/article/1046712/",
      "published": "2026-05-21T04:52:27+00:00",
      "summary": "[TV리포트=김도현 기자] 오는 22일 금요일 저녁 7시 40분 KBS 1TV에서 방영될 '황신혜의 같이 삽시다'는 고군분투하며 나 홀로 아이를 키우는 연예계 대표 싱글맘들의 동거 생활을 담은 프로그램이다. 이번 회차에서 미스코리아 진 출신이자 배우인 김지연이 싱글맘들",
      "content": "[TV리포트=김도현 기자] 오는 22일 금요일 저녁 7시 40분 KBS 1TV에서 방영될 ‘황신혜의 같이 삽시다’는 고군분투하며 나 홀로 아이를 키우는 연예계 대표 싱글맘들의 동거 생활을 담은 프로그램이다.이번 회차에서 미스코리아 진 출신이자 배우인 김지연이 싱글맘들과 이야기 나눈다.그녀는 만개한 벚꽃 길을 배경으로 싱글맘즈와 만나 자신의 인생 이야기를 공유한다. 김지연은 배우 이병헌의 동생이자 미스코리아 진 출신인 이은희와 고교 동창으로, 그의 영향을 받아 미스코리아에 도전하게 된 특별한 인연을 공개한다.그녀는 이혼 후 홈쇼핑 업계에서 연 매출 약 700억 원을 기록하며 싱글맘으로서 경제적 자립에 성공했지만, 몇 년 전 전 남자친구에게 명의를 빌려준 일로 약 10억 원의 빚을 떠안으며 인생의 큰 위기를 맞았다. 이후 김지연은 택배와 음식 배달 일을 하며 생계를 이어갔고, 어려운 상황 속에서도 긍정적인 태도를 잃지 않았다. 이에 황신혜는 “보통 여자가 아니다”라며 그녀의 강한 의지를 칭찬했다.또한, 김지연은 보험 설계사로 제2의 인생을 시작하게 된 계기를 공개한다.그녀는 배달 일을 하던 중 예상치 못한 교통사고를 겪으면서 보험의 중요성을 깨달았고, 그 경험을 바탕으로 보험 설계사에 도전하게 되었다. 현장에서 황신혜와의 즉흥적인 1:1 보험 상담을 통해 김지연은 다수의 종신 보험에 가입되어 있다는 사실과 함께 황신혜의 높은 보험료를 부담하는 뜻밖의 이유가 밝혀졌다.마지막으로, ‘황신혜의 같이 삽시다’의 시작을 함께한 장윤정과 정가은이 같이 살이를 마무리한다. 세 사람은 ‘신혜타운’ 주변을 걸으며 함께했던 소중한 추억을 되새긴다. 정가은은 힘든 순간 기댈 수 있는 언니들이 생긴 것에 대한 고마움을 전하며, 장윤정은 “오롯이 나 자신으로 살았던 시간”이었다고 털어놓으며 뭉클함을 안겼다. 이들은 서로의 버팀목이 되어준 시간을 회상하며, 새로운 인연들과 함께하는 같이 살이가 이어질 예정임을 알렸다.장윤정과 정가은의 마지막 인사는 오는 5월 22일 금요일 저녁 7시 40분 KBS 1TV ‘황신혜의 같이 삽시다’에서 확인할 수 있다.김도현 기자 / 사진 = KBS 1TV ‘황신혜의 같이 삽시다’, 김지연",
      "thumbnail_url": "https://img.tvreportcdn.de/cms-content/uploads/2026/05/21/371f3ee4-741d-4ee4-93d5-61b89642ed0c.jpg",
      "category": "K-pop",
      "priority": 2,
      "collected_at": "2026-05-21T06:30:41.819016",
      "status": "unreviewed",
      "evaluated_at": null,
      "score": null,
      "filter_reason": "K-pop 키워드: 싱글"
    },
    {
      "guid": "https://tvreport.co.kr/uncategorized/article/1046710/",
      "source": "TVReport",
      "title": "전효성, 새 둥지서 장혜진→DK와 한솥밥…메이저나인과 전속계약 체결",
      "link": "https://tvreport.co.kr/breaking/article/1046710/",
      "published": "2026-05-21T04:52:19+00:00",
      "summary": "[TV리포트=이태서 기자] 가수 및 배우 전효성이 메이저나인에서 새 출발한다. 메이저나인은 21일 \"전효성이 이달부터 당사와 전속계약을 체결해 본격적인 활동을 시작한다\"라고 밝혔다. 전효성은 지난 2009년 그룹 시크릿 멤버로 데뷔해 '샤이보이', '별빛달빛', 'PO",
      "content": "[TV리포트=이태서 기자]가수 및 배우 전효성이 메이저나인에서 새 출발한다.메이저나인은 21일 “전효성이 이달부터 당사와 전속계약을 체결해 본격적인 활동을 시작한다”라고 밝혔다.전효성은 지난 2009년 그룹 시크릿 멤버로 데뷔해 ‘샤이보이’, ‘별빛달빛’, ‘POISON(포이즌)’ 등 수많은 히트곡을 남기며 대중의 사랑을 받았다. 이후 ‘STARLIGHT(스타라이트)’, ‘항상 나를’, ‘바다빛 이야기를 찾아와’, ‘Good-night Kiss(굿나잇키스)’ 등 솔로 앨범 발매는 물론, 넷플릭스 오리지널 드라마 ‘셀러브리티’에 오민혜 역으로 출연해 배우로도 주목받았다. 뿐만 아니라 라디오 DJ 등 다양한 분야에서 활발하게 활동 중이다.메이저나인은 “전효성이 여러 분야에서 구축해온 매력이 더욱 확대될 수 있게 전폭적으로 지원할 계획이다”라며 “전효성과 메이저나인의 동행에 많은 기대 부탁드린다”라고 전했다.전효성 또한 “앞으로 다양한 방면으로 더 활발히 활동할 예정이다. 많은 응원과 사랑 부탁드린다”라고 소감을 밝혔다.한편 메이저나인에는 장혜진, 류재현(바이브), 이보람(씨야), 이창민(2am), DK(디셈버), 이솔로몬 등 다양한 음악세계를 가진 실력있는 아티스트가 소속돼 있다.이태서 기자 / 사진= 메이저나인",
      "thumbnail_url": "https://img.tvreportcdn.de/cms-content/uploads/2026/05/21/95022999-9cd4-484c-8de7-559ba05dcb88.jpg",
      "category": "K-pop",
      "priority": 2,
      "collected_at": "2026-05-21T06:30:41.820219",
      "status": "unreviewed",
      "evaluated_at": null,
      "score": null,
      "filter_reason": "K-pop 키워드: 앨범, 데뷔"
    },
    {
      "guid": "https://tvreport.co.kr/uncategorized/article/1046706/",
      "source": "TVReport",
      "title": "느닷없이 불똥 튄 아이유…MC몽 폭로 전쟁 속 애꿎은 피해자 탄생 “본인 걱정부터”",
      "link": "https://tvreport.co.kr/entertainment/article/1046706/",
      "published": "2026-05-21T04:49:33+00:00",
      "summary": "[TV리포트=김나래 기자] 연일 구설에 오르내리는 가수 MC몽이 이번에는 가수 겸 배우 아이유를 끌어들이며 또다시 대중의 비판을 받고 있다. 앞서 지난 18일부터 라이브 방송을 통해 자신의 입장을 밝혀온 MC몽은 20일에도 방송에 나타나 원정도박과 성매매 등 각종 의혹",
      "content": "[TV리포트=김나래 기자] 연일 구설에 오르내리는 가수 MC몽이 이번에는 가수 겸 배우 아이유를 끌어들이며 또다시 대중의 비판을 받고 있다.앞서 지난 18일부터 라이브 방송을 통해 자신의 입장을 밝혀온 MC몽은 20일에도 방송에 나타나 원정도박과 성매매 등 각종 의혹에 대한 억울함을 거듭 토로했다. 특히 그는 18일 방송에서 연예계 내부에 불법 도박 모임이 존재한다고 주장, 배우 김민종을 비롯한 여러 연예인의 실명을 공개해 파장을 일으킨 바 있다.전날 MC몽은 돌연 아이유 이야기를 꺼냈다.그는 “얼마 전에 ’21세기 대군부인’이 역사 왜곡으로 엄청나게 욕을 먹으면서 아이유가 고개를 숙였다”며 “정작 문제가 된 설정을 기획한 제작진은 왜 아무런 책임도 지지 않느냐”고 반문했다.이어 “얼굴 팔린 연예인은 약자다. 연예인에게 공자이길 강요하는 윗선들이 문제”라고 주장했다.실제로 해당 드라마는 11회 즉위식 장면에서 신하들이 일제히 “천세”를 외치는 장면과 중국식 다도 설정 등이 등장해 동북공정 논란을 빚었다. 이로 인해 아이유와 변우석, 제작진은 잇달아 사과문을 발표했으며 아이유는 “주연 배우로서 마땅한 책임감을 보여드리지 못한 점이 무겁고 죄송하다”고 무거운 입장을 밝혔다.그러나 MC몽의 아이유 지지 발언은 오히려 역풍을 맞았다.누리꾼들은 “본인 의혹부터 해명하고 남 걱정을 해라”, “관계도 없는 사람을 굳이 소환해 물타기하는 것 아니냐”, “아이유 입장에서는 황당할 듯”이라며 싸늘한 반응을 쏟아냈다.이미 타 연예인 실명 거론으로 논란이 되고 있는 상황에서 아이유마저 끌어들인 것을 두고 “죄 없는 피해자만 늘어나고 있다”는 비판이 이어지고 있다.김나래 기자 / 사진= TV리포트 DB, MC몽",
      "thumbnail_url": "https://img.tvreportcdn.de/cms-content/uploads/2026/05/21/5d39a54c-99e0-42e5-8f2a-277e79793639.jpg",
      "category": "K-pop",
      "priority": 2,
      "collected_at": "2026-05-21T06:30:41.822398",
      "status": "unreviewed",
      "evaluated_at": null,
      "score": null,
      "filter_reason": "K-pop 키워드: 아이유"
    },
    {
      "guid": "https://tvreport.co.kr/uncategorized/article/1046700/",
      "source": "TVReport",
      "title": "26년 전 ‘원조’ 육아 프로그램 고화질로 돌아온다…’god의 육아일기’ 4k 버전 공개",
      "link": "https://tvreport.co.kr/broadcast/article/1046700/",
      "published": "2026-05-21T04:45:27+00:00",
      "summary": "[TV리포트=이태서 기자] 온라인 동영상 서비스 웨이브(Wavve)가 관찰 예능의 대표작이자 ‘국민 예능’으로 사랑받았던 ‘god의 육아일기’ 4K 업스케일링 버전을 5월 21일 공개한다. ‘god의 육아일기’는 2000년대 초반 신인 그룹이었던 god가 아기 재민이를",
      "content": "[TV리포트=이태서 기자]온라인 동영상 서비스 웨이브(Wavve)가 관찰 예능의 대표작이자 ‘국민 예능’으로 사랑받았던 ‘god의 육아일기’ 4K 업스케일링 버전을 5월 21일 공개한다.‘god의 육아일기’는 2000년대 초반 신인 그룹이었던 god가 아기 재민이를 돌보며 벌어지는 좌충우돌 육아기를 담은 프로그램이다. god 멤버들의 풋풋한 모습과 재민이의 사랑스러운 매력이 어우러지며 당시 큰 사랑을 받았고 god의 대중적 인지도를 높인 대표 예능으로 현재까지 회자되고 있다.특히 이번 공개는 지난 5월 1일 첫 선을 보인 후 뜨거운 반응을 얻고 있는 ‘TXT의 육아일기’와 맞물려 더욱 기대를 모은다. ‘TXT의 육아일기’는 오픈 첫날 웨이브 신규 유료 가입 견인 콘텐츠 1위를 기록하며 화제성을 입증한 바 있다.향후 공개될 ‘TXT의 육아일기’ 회차에는 god 손호영과 김태우가 출연할 예정으로, ‘육아일기’ 원조 멤버와 TXT의 만남을 통해 세대를 잇는 재미를 더할 전망이다. 웨이브는 이 같은 흐름에 맞춰 원조 콘텐츠인 ‘god의 육아일기’ 4K 업스케일링 버전을 선보이며 ‘육아일기’ 콘텐츠에 대한 관심을 한층 확장할 계획이다.이번 고화질 리마스터링을 통해 시청자들은 과거 브라운관 시절의 아쉬운 화질을 벗어나 멤버들의 리얼한 표정과 재민이의 사랑스러운 모습을 한층 선명해진 해상도로 감상할 수 있게 됐다. 원작의 추억을 공유하는 팬들에게는 깊은 향수를, ‘TXT의 육아일기’로 새롭게 유입된 시청자들에게는 원조 명작을 트렌디하게 발견하는 재미를 선사할 것으로 보인다.‘god의 육아일기’ 4K 업스케일링 버전은 21일 웨이브에서 전 회차 공개된다.이태서 기자 / 사진= TV리포트 DB, 웨이브(Wavve)",
      "thumbnail_url": "https://img.tvreportcdn.de/cms-content/uploads/2026/05/21/8b73631e-037d-4018-be28-74c2c760d514.jpg",
      "category": "K-pop",
      "priority": 2,
      "collected_at": "2026-05-21T06:30:41.827325",
      "status": "unreviewed",
      "evaluated_at": null,
      "score": null,
      "filter_reason": "K-pop 키워드: TXT"
    },
    {
      "guid": "https://tvreport.co.kr/uncategorized/article/1046698/",
      "source": "TVReport",
      "title": "박명수, 전쟁으로 경제 상황 악화→또 소신 발언…”전기세 안 올린 게 어디냐” (‘라디오쇼’)",
      "link": "https://tvreport.co.kr/entertainment/article/1046698/",
      "published": "2026-05-21T04:45:02+00:00",
      "summary": "[TV리포트=윤희정 기자] 코미디언 박명수가 경제 상황과 관련된 소신을 밝혔다. 20일 방송된 KBS 쿨FM '박명수의 라디오쇼'(이하 '라디오쇼')에서는 고민을 해결해 주는 코너 '명수초이스'가 진행됐다. 이날 한 청취자는 빨래를 돌려야 하는데 양이 애매하다고 문자를",
      "content": "[TV리포트=윤희정 기자] 코미디언 박명수가 경제 상황과 관련된 소신을 밝혔다.20일 방송된 KBS 쿨FM ‘박명수의 라디오쇼'(이하 ‘라디오쇼’)에서는 고민을 해결해 주는 코너 ‘명수초이스’가 진행됐다.이날 한 청취자는 빨래를 돌려야 하는데 양이 애매하다고 문자를 남겼다. 그는 “지금 돌릴지, 내일 돌릴지 고민된다”라고 토로했다. 박명수는 한 치의 고민도 없이 “(빨랫감을) 더 쌓아서 내일 돌리는 게 좋다”라고 답했다.이어 그는 “전기세 아껴야 한다. 지금 국제 유가다 뭐다 해서 난리이지 않냐”라고 설명했다. 국제 유가 상승과 물가 부담을 이유로 이를 언급한 것.현재 국제 유가는 미국과 이란의 종전 협상, 호르무즈 해협 개방 여부 등의 불확실성이 이어지면서 당분간 높은 수준을 유지할 전망이다. 박명수는 “지금 전기세 안 올린 게 어디냐. 그나마 다행인 거다”라며 “한꺼번에 몰아서 하시는 게 저는 좋을 것 같다”라고 덧붙였다.박명수의 고민 상담은 계속됐다. 다른 청취자는 “설거지하기 귀찮은데, 식기 세척기를 살지 말지 고민된다”라고 물었다. 이를 듣던 박명수는 “이것도 참 어렵다. 식기 세척기를 파는 분들이 계시지 않냐. 내가 사지 말라고 하기가 참 애매모호하다”라면서도 “우리 집도 식기 세척기가 있는데, 귀찮아서 잘 안 쓴다”라고 밝혔다. 그는 “그냥 설거지하면서 그 돈은 갖고 계시다가 나중에 식사할 가족들이 많을 때 사라”라고 조언했다.1993년 MBC 4기 공채 개그맨으로 데뷔한 박명수는 평소 사회 이슈에 대한 솔직하고 직설적인 소신 발언으로 대중의 지지를 받고 있다.앞서 지난 4월 그는 ‘라디오쇼’에서 “솔직히 버릴 말도 많다”라며 “나도 걱정 없는 사람 아니고 그렇게 말하고 나서 후회할 때도 많다”라고 밝힌 바 있다. 당시 박명수는 “내 말을 다 믿지 말고, 9시 뉴스에 나올 만한 말이나 공식 석상에서 한 이야기만 믿어달라”라고 당부했다.윤희정 기자 / 사진=TV리포트 DB, KBS 쿨FM ‘박명수의 라디오쇼’",
      "thumbnail_url": "https://img.tvreportcdn.de/cms-content/uploads/2026/05/20/5ba8b2bf-c291-4945-b77e-c12d210ad823.jpg",
      "category": "K-pop",
      "priority": 2,
      "collected_at": "2026-05-21T06:30:41.828945",
      "status": "unreviewed",
      "evaluated_at": null,
      "score": null,
      "filter_reason": "K-pop 키워드: 데뷔"
    },
    {
      "guid": "https://tvreport.co.kr/uncategorized/article/1046696/",
      "source": "TVReport",
      "title": "‘플라이투더스카이’ 환희, 과거 불화설 언급…”그때 쓰레기통을 다” (‘전현무계획3’)",
      "link": "https://tvreport.co.kr/broadcast/article/1046696/",
      "published": "2026-05-21T04:44:48+00:00",
      "summary": "[TV리포트=송시현 기자] MBN·채널S의 ‘전현무계획3’에서 전현무, 환희, 브라이언이 ‘골드미스터 연합’을 결성한다. 22일(금) 밤 9시 10분 방송되는 본격 리얼 길바닥 먹큐멘터리 ‘전현무계획3’ 32회에서는 전현무와 곽튜브(곽준빈) 그리고 플라이투더스카이의 환",
      "content": "[TV리포트=송시현 기자] MBN·채널S의 ‘전현무계획3’에서 전현무, 환희, 브라이언이 ‘골드미스터 연합’을 결성한다.22일(금) 밤 9시 10분 방송되는 본격 리얼 길바닥 먹큐멘터리 ‘전현무계획3’ 32회에서는 전현무와 곽튜브(곽준빈) 그리고 플라이투더스카이의 환희와 브라이언이 강원도 강릉에서 ‘빨간 맛’ 특집 먹트립을 선보인다.이날 네 사람은 강릉 중앙시장에서 상인들이 추천한 ‘삼세기(삼숙이)’ 맛집으로 직행한다. 잠시 후 피라냐를 연상케 하는 비주얼의 삼숙이 탕이 등장하자 모두는 얼큰한 국물과 부드러운 생선 살의 조합에 빠져들어 폭풍 먹방을 펼친다.먹방 중,곽튜브가 플라이투더스카이의 불화설을 조심스레 언급하며 “아직도 사람들이 화해했냐고 물어보지 않냐”고 질문한다. 환희는 “지금은 (사이가) 괜찮아졌냐고 많이들 물으신다”고 쿨하게 인정한 뒤, 과거 무대 직전 다퉜던 이야기를 꺼내며 “그때 쓰레기통을 다…”라고 언급해 궁금증을 유발한다. 이를 들은 브라이언은 “여기 소주 한 병 주세요~”라고 농담하며 분위기를 밝히고, 환희는 “무대를 하고 나면 자연스럽게 풀렸다.어렸을 때라 먹는 걸로도 싸우고 별거 아닌 일로 다퉜다”고 현실적인 형제 케미를 드러낸다.이어 전현무는 “나는 브라이언이 괜히 반갑다. 왠지 결혼 안 할 것 같아서”라며 묘한 동질감을 보인다. 브라이언은 “환희도 안 했는데?”라고 억울해하고, 환희는 “사실 브라이언 꿈이 서른 살 전에 결혼하는 것이었다”고 폭로한다. 브라이언은 “나이가 들다 보니 혼자가 익숙해졌다. 이젠 영원히 혼자 있어야겠다는 생각도 든다”고 비혼에 대한 생각을 솔직히 밝힌다. 전현무는 “연애 생각도 없어 보인다”고 지적하고, 브라이언은 “나는 솔로 17년 차”라며 씁쓸한 모습을 보인다. 환희 역시 “전 가끔 썸은 타는 데 오래 못 간다”고 털어놓는다. 이에 전현무는 폭풍 공감을 표하며 “오늘이 축제다!”라고 외쳐 웃음을 자아낸다.강릉의 ‘빨간 맛’만큼이나 화끈했던 전현무, 환희, 브라이언의 ‘노필터 싱글 토크’는 22일(금) 밤 9시 10분 방송되는 MBN·채널S ‘전현무계획3’에서 확인할 수 있다.송시현 / 사진 = MBN·채널S ‘전현무계획3’",
      "thumbnail_url": "https://img.tvreportcdn.de/cms-content/uploads/2026/05/21/8fb18ef3-05f1-4c3c-a191-518550e6a30e.jpg",
      "category": "K-pop",
      "priority": 2,
      "collected_at": "2026-05-21T06:30:41.830270",
      "status": "unreviewed",
      "evaluated_at": null,
      "score": null,
      "filter_reason": "K-pop 키워드: 싱글"
    }
  ]
}