{
  "last_updated": "2026-06-17T10:30:51.938596",
  "items": [
    {
      "guid": "https://www.yna.co.kr/view/AKR20260617153600005",
      "source": "연합뉴스_엔터",
      "title": "[가요소식] 밴드 넬, 10집 'X'…\"감사하고 뿌듯\"",
      "link": "https://www.yna.co.kr/view/AKR20260617153600005",
      "published": "2026-06-17T17:47:45+09:00",
      "summary": "(서울=연합뉴스) 이태수 기자 = ▲ 넬 10집 'X' 발표 = 밴드 넬이 17일 정규 10집 'X'를 발표했다고 소속사 스페이스 보헤미안이 밝...",
      "content": "이태수\n기자\n구독\n구독중\n이전\n다음\n3호선버터플라이 드러머 서현정, 첫 솔로 정규앨범\n이미지 확대\n넬 10집 'X'\n[스페이스 보헤미안 제공. 재판매 및 DB 금지]\n(서울=연합뉴스) 이태수 기자 = ▲ 넬 10집 'X' 발표 = 밴드 넬이 17일 정규 10집 'X'를 발표했다고 소속사 스페이스 보헤미안이 밝혔다.\n스페이스 보헤미안은 \"앨범명 'X'는 열 번째 정규앨범을 뜻하는 로마 숫자 '10'인 동시에, 특정한 의미로 규정되지 않는다는 미지수의 상징\"이라고 소개했다.\n멤버들은 신보에 얼터너티브 록, 모던 록, 슈게이징 등 다양한 장르를 담아냈다.\n타이틀곡 '스위트 딜루젼'(Sweet Delusion)은 청량한 모던 록 사운드에 신념과 희망의 정서를 녹여낸 노래다. 강렬한 얼터너티브 록 사운드가 인상적인 곡으로, 넬은 데뷔 이래 처음으로 녹음에 브라스 세션도 활용했다.\n넬은 소속사를 통해 \"10집이라서 특별하다기보다는, 늘 그랬듯 이전보다 더 좋은 앨범을 만들고 싶었다\"며 \"다만 한국에서 30년 가까이 활동하며 정규앨범 10장을 발표할 수 있다는 사실은 분명 감사하고 뿌듯한 일\"이라고 소감을 전했다.\n넬은 올여름 다양한 음악 축제 무대 등을 통해 팬들을 만날 계획이다.\n이미지 확대\nSØHJ(서현정)\n[튜나 레이블 제공. 재판매 및 DB 금지]\n▲ 3호선버터플라이 서현정, 솔로 정규앨범 = 밴드 3호선버터플라이의 드러머 서현정(SØHJ)이 오는 21일 첫 솔로 정규앨범 'Ø: 비트윈(Between)'을 낸다고 튜나 레이블이 밝혔다.\n서현정 측은 \"제목에 쓰인 'Ø'는 공집합이면서 동시에 무한한 가능성을 품은 원형의 상징으로, 끊임없이 변화하고 움직이는 존재의 상태를 의미한다\"고 설명했다.\n앨범에는 선공개된 싱글 '어나더 럴러바이'(Another Lullaby)와 '딥 블루 다이브'(Deep Blue Dive)를 포함해 총 10곡이 담긴다.\n서현정은 오랜 시간 드러머로 쌓은 리듬감과 음악적 경험을 이번 솔로 앨범에서는 전자음악이라는 새로운 형태로 확장했다.\ntsl@yna.co.kr\n관련 뉴스\n넬, 10집 앞두고 미니앨범 발표…타이틀곡 '딥 인사이드'\n제보는 카카오톡 okjebo\n<저작권자(c) 연합뉴스,\n무단 전재-재배포, AI 학습 및 활용 금지>\n2026/06/17 17:47 송고\n2026년06월17일 17시47분 송고\n#넬\n#밴드\n댓글\n좋아요\n슬퍼요\n화나요\n후속요청\n국내 최대 원스톱\n콘텐츠 제공 플랫폼\n함께 보면 좋은 콘텐츠\nby\n데이블\n광고\n함께 읽기 좋은 콘텐츠\nTaboola 후원링크\n광고\n광고\n광고\n연합 마이뉴스\n다양한 주제별 맞춤\n추천 뉴스를 제공합니다.\n북마크\n공유\n공유하기\n카카오톡\n페이스북\nX\n페이스북 메신저\n네이버 밴드\nURL 복사\n닫기\nURL이 복사되었습니다.\n댓글\n글자크기\n본문 글자 크기 조정\n폰트 1단계 13px\n폰트 2단계 16px\n폰트 3단계 18px\n폰트 4단계 20px\n폰트 5단계 22px\n닫기\n프린트\n제보",
      "thumbnail_url": "https://img.yna.co.kr/etc/inner/KR/2026/06/17/AKR20260617153600005_01_i_P2.jpg",
      "category": "K-pop",
      "priority": 1,
      "collected_at": "2026-06-17T10:30:42.540612",
      "status": "unreviewed",
      "evaluated_at": null,
      "score": null,
      "filter_reason": "K-pop 키워드: 앨범, 미니앨범, 싱글, 타이틀곡, 데뷔"
    },
    {
      "guid": "https://sports.donga.com/ent/article/all/20260617/134131454/1",
      "source": "스포츠동아",
      "title": "혜리, 뱃살 논란 의식? 당당한 노출 의상",
      "link": "https://sports.donga.com/ent/article/all/20260617/134131454/1",
      "published": "2026-06-17T17:39:57+09:00",
      "summary": "[동아닷컴 최윤나 기자] 가수 겸 배우 혜리가 팬미팅 이후 불거진 몸매 관련 반응에 직접 입장을 밝힌 가운데, 무대 뒤 비하인드 사진을 공개해 눈길을 끈다.혜리는 지난 16일 자신의 SNS에 팬미팅 현장에서 촬영한 여러 장의 사진을 게재했다. 공개된 사진에는 다양한 무대 의상을 입고 포즈를 취하는 혜리의 모습이 담겼다. 화려한 스타일링과 늘씬한 비율, 자신감 넘치는 분위기가 시선을 사로잡았다.앞서 혜리는 지난 13일 서울 이화여자대학교 삼성홀에서 열린 ‘2026 HYERI ASIA TOUR FANMEETING IN SEOUL’ 이후 일부 온라인 커뮤니티를 중심으로 몸매 관련 반응이 나오며 이른바 ‘뱃살 논란’에 휩싸였다.이와 관련해 혜리는 16일 팬 소통 플랫폼을 통해 “사실 나는 내가 좋지만 보는 사람들은 프로답지 못하다고 생각할 수 있으니”라며 “(근데 왜 꼭 날씬해야 프로 같은 건지는 모르겠지만) 그래도 혜루미가 원한다면 애써볼게! 운동도 하고 건강하게”라고 솔직한 생각",
      "content": "",
      "thumbnail_url": "https://dimg.donga.com/wps/SPORTS/FEED/SD_MAIN_2018/134131460.1.thumb.jpg",
      "category": "K-pop",
      "priority": 2,
      "collected_at": "2026-06-17T10:30:43.647856",
      "status": "unreviewed",
      "evaluated_at": null,
      "score": null,
      "filter_reason": "K-pop 키워드: 팬미팅"
    },
    {
      "guid": "2026061718520809390",
      "source": "MyDaily_스타",
      "title": "원더걸스 혜림, 7년 열애 끝 결혼했는데…\"다른 남자 더 만나볼 걸\" 뜻밖의 후회",
      "link": "https://www.mydaily.co.kr/page/view/2026061718520809390",
      "published": "2026-06-17T19:21:28+09:00",
      "summary": "[마이데일리 = 한소희 기자] 그룹 원더걸스 출신 혜림이 결혼과 연애에 대한 솔직한 생각을 털어놨다.\n\n17일 유튜브 채널 '노빠꾸탁재훈'에는 '원더걸스 선예 혜림, 아이돌에서 아이 다섯이 된 한 시대를 풍미했던 K-POP의 선구자'라는 제목의 영상이 공개됐다.\n이날 혜림은 남편 신민철과 처음 만나게 된 계기를 공개했다. 그는 \"아버지가 태권도장을 운영하시는데, 태권도 관련 모임에 따라갔다가 남편을 처음 만났다\"며 \"당시 남편도 태권도를 하고 있었다\"고 설명했다.\n이어 탁재훈은 \"연애 시절 다른 남자도 만나보고 싶어서 주기적으로 헤어지자고 했다는 이야기가 있더라\"고 물었고, 혜림은 이를 인정하며 연애 당시를 떠올렸다.\n혜림은 \"남편과 오랜 기간 교제했지만 양다리를 걸칠 생각은 전혀 없었다\"며 \"헤어졌다가 다른 사람을 잠깐 만나보고, 다시 만나기를 반복한 적은 있다\"고 솔직하게 말했다.\n\n이에 탁재훈이 \"지금 남편과 결혼한 것을 후회한 적은 없느냐\"고 묻자 혜림은 웃으며 \"27살에 결혼했는데 지금 생각하면 조금 더 다양한 사람을 만나볼 걸 하는 아쉬움은 있다\"고 답했다.\n특히 그는 \"래퍼나 셰프와는 한 번쯤 연애해봤으면 어땠을까 싶다\"며 \"요리를 잘하는 남자도 매력적이고, 래퍼들의 세계도 궁금하다\"고 덧붙여 현장을 웃음바다로 만들었다.\n\n함께 출연한 선예 역시 남편과의 인연을 전했다. 선예는 \"남편이 아이티에서 선교 및 구호 활동을 하고 있었는데, 그 과정에서 자연스럽게 만나게 됐다\"고 밝혔다.\n\n이를 들은 탁재훈은 \"선예 씨는 원래 선한 이미지가 있고, 혜림 씨는 천진난만한 매력이 있다\"며 특유의 입담을 뽐냈고, 두 사람 역시 고개를 끄덕이며 공감했다.\n\n한편, 혜림은 태권도 선수 출신 신민철과 7년간의 열애 끝에 2020년 결혼했으며, 현재 두 아들을 두고 있다. 선예는 슬하에 세 자녀를 두고 있다.",
      "content": "[마이데일리 = 한소희 기자] 그룹 원더걸스 출신 혜림이 결혼과 연애에 대한 솔직한 생각을 털어놨다.17일 유튜브 채널 '노빠꾸탁재훈'에는 '원더걸스 선예 혜림, 아이돌에서 아이 다섯이 된 한 시대를 풍미했던 K-POP의 선구자'라는 제목의 영상이 공개됐다.이날 혜림은 남편 신민철과 처음 만나게 된 계기를 공개했다. 그는 \"아버지가 태권도장을 운영하시는데, 태권도 관련 모임에 따라갔다가 남편을 처음 만났다\"며 \"당시 남편도 태권도를 하고 있었다\"고 설명했다.이어 탁재훈은 \"연애 시절 다른 남자도 만나보고 싶어서 주기적으로 헤어지자고 했다는 이야기가 있더라\"고 물었고, 혜림은 이를 인정하며 연애 당시를 떠올렸다.혜림은 \"남편과 오랜 기간 교제했지만 양다리를 걸칠 생각은 전혀 없었다\"며 \"헤어졌다가 다른 사람을 잠깐 만나보고, 다시 만나기를 반복한 적은 있다\"고 솔직하게 말했다.이에 탁재훈이 \"지금 남편과 결혼한 것을 후회한 적은 없느냐\"고 묻자 혜림은 웃으며 \"27살에 결혼했는데 지금 생각하면 조금 더 다양한 사람을 만나볼 걸 하는 아쉬움은 있다\"고 답했다.특히 그는 \"래퍼나 셰프와는 한 번쯤 연애해봤으면 어땠을까 싶다\"며 \"요리를 잘하는 남자도 매력적이고, 래퍼들의 세계도 궁금하다\"고 덧붙여 현장을 웃음바다로 만들었다.함께 출연한 선예 역시 남편과의 인연을 전했다. 선예는 \"남편이 아이티에서 선교 및 구호 활동을 하고 있었는데, 그 과정에서 자연스럽게 만나게 됐다\"고 밝혔다.이를 들은 탁재훈은 \"선예 씨는 원래 선한 이미지가 있고, 혜림 씨는 천진난만한 매력이 있다\"며 특유의 입담을 뽐냈고, 두 사람 역시 고개를 끄덕이며 공감했다.한편, 혜림은 태권도 선수 출신 신민철과 7년간의 열애 끝에 2020년 결혼했으며, 현재 두 아들을 두고 있다. 선예는 슬하에 세 자녀를 두고 있다.많이 본 뉴스하이닉스 245만원인데…조혜련 \"87만원에 매수\"→신기루 \"난 146만원\" [마데핫리뷰]미초바, ♥빈지노 또 반할라…명품 비키니 '자태'김진경 \"남편 김승규 월드컵 선방쇼, 사람들은 분유 버프라고…\"",
      "thumbnail_url": "https://img.mydaily.co.kr/photos/2026/06/17/2026061719193493676_l.png",
      "category": "K-pop",
      "priority": 2,
      "collected_at": "2026-06-17T10:30:49.635149",
      "status": "unreviewed",
      "evaluated_at": null,
      "score": null,
      "filter_reason": "K-pop 키워드: 아이돌"
    },
    {
      "guid": "https://tvreport.co.kr/uncategorized/article/1054645/",
      "source": "TVReport",
      "title": "‘대세 ★’가 되면 거치는 과정인가…변우석→손종원·허남준, 황당 열애설에 ‘몸살’ [종합]",
      "link": "https://tvreport.co.kr/star/article/1054645/",
      "published": "2026-06-17T10:00:02+00:00",
      "summary": "[TV리포트=민세윤 기자] 최근 연예계와 방송가에는 급상승한 인기와 함께 황당한 온라인 발 루머로 몸살을 앓는 스타들이 늘고 있다. 개인 계정 게시물 하나, 팔로우 목록 하나를 현미경처럼 살피며 '네티즌 수사대'를 자처한 이들의 추측성 주장이 기정사실로 되자, 결국 당",
      "content": "[TV리포트=민세윤 기자] 최근 연예계와 방송가에는 급상승한 인기와 함께 황당한 온라인 발 루머로 몸살을 앓는 스타들이 늘고 있다. 개인 계정 게시물 하나, 팔로우 목록 하나를 현미경처럼 살피며 ‘네티즌 수사대’를 자처한 이들의 추측성 주장이 기정사실로 되자, 결국 당사자들이 직접 나서서 “사실무근”을 외치며 진화에 나서는 상황이 반복되는 중이다.가장 최근 억울한 루머의 중심에 선 주인공은 SBS 드라마 ‘멋진 신세계’로 최고의 주가를 올리고 있는 배우 허남준이다. 일부 네티즌들은 허남준의 개인 계정 팔로우 목록을 살피던 중, 그와 함께 드라마에 출연 중인 모델 겸 배우 홍이설이 맞팔로우 상태라는 점을 근거로 열애 의혹을 제기했다. 해당 의혹은 순식간에 각종 온라인 커뮤니티로 퍼졌고, 캐스팅 의혹 등의 악성 루머로까지 변질됐다.결국 참다못한 홍이설이 지난 13일 자신의 계정을 통해 직접 장문의 해명 글을 올렸다. 홍이설은 “언급되고 있는 배우님(허남준)과는 대학 시절 수업을 같이 들으며 친해진 좋은 동료 사이일 뿐, 열애설은 전혀 사실이 아니”라고 선을 그었다. 이어 “계속되는 추측들로 인해 상대 배우님께 폐가 될 것 같아 직접 말씀드리게 됐다”며 “드라마 관련 이야기들 또한 모두 사실이 아니니 걱정하지 않으셔도 된다”고 답답한 심경을 토로했다.그런가 하면 마침 올린 반려견 사진이 비슷하다는 이유만으로 뜬금없는 열애설에 휩싸인 대세 셰프도 있다. 넷플릭스 ‘흑백요리사2’와 JTBC ‘냉장고를 부탁해’를 통해 예능 블루칩으로 떠오른 손종원 셰프는 모델 여연희와 황당한 스캔들에 휘말렸다. 두 사람의 개인 계정에 등장한 강아지의 종과 배경이 유사하다는 이유로 네티즌들이 접점을 찾아 나선 것.이에 여연희는 자신의 채널을 통해 쿨하면서도 확실하게 루머를 전면 부인했다. 여연희는 “사귄다는 글이 올라왔다는데 아예 아니다. 실제로 아는 오빠일 뿐”이라고 못을 박았다. 이어 “오빠가 올린 강아지 사진이 내 반려견과 너무 닮았지만 전혀 다른 강아지”라고 설명하며 “오빠가 인기가 많아서 열애설 자체는 기분 나쁘지 않지만, 악플을 남긴 네티즌들에게는 똑똑하니까 아직까지 일하는 것”이라고 일침을 날리기도 했다.신드롬급 인기를 구가하며 역대급 대세로 거듭난 배우 변우석 역시 ‘럽스타그램’이라는 꼬리표로 곤혹을 치렀다. 변우석은 tvN ‘선재 업고 튀어’ 종영 이후 모델 전지수와 같은 장소에서 찍은 사진을 개인 계정에 업로드하고 커플 반지를 착용했다는 의혹을 받으며 열애설이 확산됐다.추측이 걷잡을 수 없이 커지자 변우석의 소속사 바로엔터테인먼트 측은 “두 사람의 열애설은 전혀 사실이 아니”라며 즉각 공식 입장을 냈다. 소속사 측은 두 사람이 대학 시절부터 절친한 친구 사이로 지인들과 함께했던 자리였을 뿐이라며 선을 그었다. 이후 언론 보도를 통해 전지수가 당시 유명 DJ와 열애 중이라는 사실이 단독으로 전해지면서 변우석과의 럽스타그램 의혹은 해프닝으로 완전하게 종결됐다.이처럼 허남준, 손종원, 변우석 등 대중의 주목을 받는 대세 스타들이 겪는 ‘커뮤니티 발 열애설’의 풍경은 씁쓸함을 남긴다. 이에 대중 또한 “하나하나 감시하듯 살피는 게 너무 무섭다”, “사소한 추측이 악의적인 루머로 변질되는 것은 큰 문제”라며 우려의 목소리를 높이고 있다. 단순한 관심의 표현을 넘어 당사자들에게 피해를 주는 무분별한 억측 자제가 필요한 시점이다.민세윤 기자 / 사진=TV리포트 DB, 홍이설, JTBC ‘냉장고를 부탁해’",
      "thumbnail_url": "https://img.tvreportcdn.de/cms-content/uploads/2026/06/15/b1f3f356-cb5f-41df-bd83-f1d14185c8ce.jpg",
      "category": "K-pop",
      "priority": 2,
      "collected_at": "2026-06-17T10:30:51.848836",
      "status": "unreviewed",
      "evaluated_at": null,
      "score": null,
      "filter_reason": "K-pop 키워드: 리사"
    },
    {
      "guid": "https://tvreport.co.kr/uncategorized/article/1054641/",
      "source": "TVReport",
      "title": "한정민♥유다연, 재혼 1년 만에 갈등 직면…”실수할 때마다 이혼 생각나” (‘이호선상담소’)",
      "link": "https://tvreport.co.kr/entertainment/article/1054641/",
      "published": "2026-06-17T09:17:37+00:00",
      "summary": "[TV리포트=정대진 기자] '돌싱글즈3' 출신 한정민이 초혼인 아내 유다연과의 결혼 생활에서 느끼는 재혼의 부담감과 육아 갈등을 솔직하게 고백했다. 16일 방송된 tvN STORY 예능 '이호선 상담소'에는 한정민, 유다연 부부가 출연해 재혼 1년 만에 마주한 현실적인",
      "content": "[TV리포트=정대진 기자] ‘돌싱글즈3’ 출신 한정민이 초혼인 아내 유다연과의 결혼 생활에서 느끼는 재혼의 부담감과 육아 갈등을 솔직하게 고백했다.16일 방송된 tvN STORY 예능 ‘이호선 상담소’에는 한정민, 유다연 부부가 출연해 재혼 1년 만에 마주한 현실적인 부부 갈등을 털어놨다.두 사람은 지난해 7월 결혼과 임신 소식을 알린 뒤 같은 해 9월 첫 딸을 품에 안았으나, 출산 이후 8개월 동안 지속적인 다툼을 이어오고 있다고 밝혀 안타까움을 자아냈다.이날 유다연은 육아보다 자기 관리를 우선시하는 한정민의 태도에 섭섭함을 토로했다. 유다연은 “남편이 너무 이기적이고 자기만 생각한다”며 “아이랑 셋이 외출하면 아이 물품을 챙기는 것보다 본인 외모를 더 신경 쓴다”고 폭로했다.이어 남편 본인도 산후우울증이 왔다며 헬스장과 피부과를 보내달라고 요구한 점을 언급하며 “결혼을 후회하기도 했다”고 덧붙였다.아울러 아이에게 매정하게 구는 모습을 지적하며 “남편은 아이가 감정 없이 독립적으로 잘 컸으면 좋겠다고 한다”며 “‘이유식을 주면 바로 먹고 침대에 눕히면 바로 잤으면 좋겠다’며 화를 내 속상하다”고 털어놨다.반면 한정민은 아내의 퉁명스러운 말투에 깊은 상처를 받고 있었다. 한정민은 “‘지가’ 같은 말들이 아무렇지 않게 나온다”며 “‘너나 먹어’ 이런 말들이 불편하다”고 서운함을 내비쳤다. 또한 육아로 인해 집안에만 갇혀 지내며 우울감을 느꼈던 심경을 전하며 “아이보다는 부부의 행복이 우선”이라는 가치관을 설명했다. 임신 중 아침 6시에 귀가했던 사건에 대해서는 평소 회식에 참석하지 않다가 ‘돌싱글즈’ 모임 때 딱 한 번 있었던 이례적인 일이었다고 해명했다.특히 한정민은 한 번의 아픔을 겪은 후 재혼한 상태이기에 아내에게 늘 미안한 마음을 품고 살았다고 고백했다.한정민은 “실수할 때마다 ‘이래서 내가 이혼했나’ 생각도 든다”고 눈물을 흘려 보는 이들의 마음을 먹먹하게 만들었다.초혼인 유다연에게 더 잘해야 한다는 압박감이 스스로를 옥죄고 있었던 셈.두 사람의 이야기를 들은 이호선은 남편이 이기적인 면이 있으나 방법을 잘 몰라서 그랬을 것이라며 위로를 건넸다. 이호선은 “남편은 아내를 좋아하고 아내는 아이를 좋아한다. 두 사람은 술래잡기 중”이라며 최선을 다하고 있음에도 인정받지 못해 외로워하는 남편의 상태를 진단했다. 이어 갈등 해결을 위해 하루 세 가지씩 감사한 일 나누기, 서로를 존중할 수 있는 ‘~씨’로 호칭 부르기 등의 구체적인 솔루션을 제시하며 부부의 앞날을 응원했다.정대진 기자 / 사진= 한정민,  tvN STORY ‘이호선 상담소’",
      "thumbnail_url": "https://img.tvreportcdn.de/cms-content/uploads/2026/06/17/179c482d-456a-493b-bb61-060ba0e1e506.jpg",
      "category": "K-pop",
      "priority": 2,
      "collected_at": "2026-06-17T10:30:51.851127",
      "status": "unreviewed",
      "evaluated_at": null,
      "score": null,
      "filter_reason": "K-pop 키워드: 싱글"
    },
    {
      "guid": "https://tvreport.co.kr/uncategorized/article/1054631/",
      "source": "TVReport",
      "title": "故이서이, 모교 한국외대에 장학금 2억 기부",
      "link": "https://tvreport.co.kr/star/article/1054631/",
      "published": "2026-06-17T08:48:51+00:00",
      "summary": "[TV리포트=이혜미 기자] 지난해 고인이 된 배우 이서이가 모교에 장학금을 기부했다. 17일 한국외국어대학교(이하 한국외대)에 따르면 고인의 유족은 학교 측에 2억 원의 장학금을 전달했다. 고인의 사망 1주기를 4일 앞둔 지난 16일 한국외대 글로벌캠퍼스에서 열린 장학",
      "content": "[TV리포트=이혜미 기자] 지난해 고인이 된 배우 이서이가 모교에 장학금을 기부했다.17일 한국외국어대학교(이하 한국외대)에 따르면 고인의 유족은 학교 측에 2억 원의 장학금을 전달했다.고인의 사망 1주기를 4일 앞둔 지난 16일 한국외대 글로벌캠퍼스에서 열린 장학금 전달식에는 고인의 가족과 지인, 학과 교수 등이 참석해 수여식을 진행하고 어문광장 앞 잔디광장에 느티나무를 심어 고인을 기렸다.학교 측은 매년 4월 장학생 2명을 선발해 생활비 등을 장학금으로 지원할 예정이다.1982년생인 고 이서이는 지난해 6월 20일 세상을 떠났다. 향년 43세.지난 2013년 MBC 드라마 ‘구암 허준’을 통해 데뷔한 고인은 ‘백년의 유산’, ‘청담동 스캔들’, 연극 ‘굿닥터’, 영화 ‘상의원’, ‘마담뺑덕’, ‘더킹’. ‘환상동화’, ‘아직 사랑하고 있습니까’ 등 다양한 작품에 출연하며 몰입력 높은 연기력으로 대중의 사랑을 받았다.고인은 한국외대 체코·슬로바키아학과 출신으로 재학 당시 학생회장으로 활동했던 것으로 알려졌다.이혜미 기자 / 사진 = 이서이 소셜",
      "thumbnail_url": "https://img.tvreportcdn.de/cms-content/uploads/2026/06/17/796f7e95-f107-4d1c-91a6-bd19eef9ae43.jpg",
      "category": "K-pop",
      "priority": 2,
      "collected_at": "2026-06-17T10:30:51.856631",
      "status": "unreviewed",
      "evaluated_at": null,
      "score": null,
      "filter_reason": "K-pop 키워드: 데뷔"
    },
    {
      "guid": "https://tvreport.co.kr/uncategorized/article/1054627/",
      "source": "TVReport",
      "title": "출연료만 ‘970억’ 대어 낚았다…9년 만 컴백→올여름 극장가 뒤집을 美 영화",
      "link": "https://tvreport.co.kr/movie/article/1054627/",
      "published": "2026-06-17T08:45:39+00:00",
      "summary": "[TV리포트=김나래 기자] 원작 애니메이션에서 마우이 목소리를 연기했던 배우 드웨인 존슨이 실사 영화 '모아나'에서 직접 마우이로 변신했다. 영화 '모아나'는 바다가 선택한 소녀 모아나가 전설의 영웅 마우이와 함께 저주에 걸린 섬을 구하기 위해 미지의 바다로 나서는 여",
      "content": "[TV리포트=김나래 기자] 원작 애니메이션에서 마우이 목소리를 연기했던 배우 드웨인 존슨이 실사 영화 ‘모아나’에서 직접 마우이로 변신했다.영화 ‘모아나’는 바다가 선택한 소녀 모아나가 전설의 영웅 마우이와 함께 저주에 걸린 섬을 구하기 위해 미지의 바다로 나서는 여정을 그린 올여름 기대작이다.마우이 역을 맡은 존슨이 캐릭터 완성을 위해 가장 공들인 부분은 특수 분장과 전신 의상이었다. 마우이 특유의 외형을 살리기 위해 착용한 보철물, 가발, 의상의 무게는 약 18kg에 달했으며, 무더운 날씨에 장시간 이를 착용하고 촬영하는 일은 만만치 않은 도전이었다. 그는 “실제 바디슈트를 입으면 촉각적이고 감정적인 공감대가 생긴다. 마치 몸과 함께 움직이고 숨 쉬는 것 같았다”며 캐릭터에 몰입하기 위해 기꺼이 그 과정을 감내했다고 밝혔다.외형 구현에 그치지 않고 존슨은 체중 증량까지 감행하며 마우이의 다부진 체격을 만들어냈고, 촬영 기간 내내 이를 유지했다. 무거운 장비를 착용한 상태에서도 자연스러운 움직임과 감정 표현을 끌어내기 위해 각고의 노력을 기울였다는 점도 눈길을 끈다.존슨에게 마우이는 단순한 배역을 넘어선 의미를 지닌다. 애니메이션에서 목소리로만 연기했던 캐릭터를 이번에는 직접 몸으로 구현해낸 것이다. 사모아계 혈통인 그는 평소 폴리네시아 문화에 깊은 애정을 드러내 왔으며, 이 작품 역시 자신의 뿌리와 맞닿아 있는 특별한 프로젝트라고 강조했다.존슨은 “어떤 역경 속에서도 폴리네시아 사람들에게는 본질적인 문화적 사랑과 기쁨이 남아 있다. 스토리와 개발 전 과정에서 폴리네시아 문화를 제대로 담아내려 최선을 다했다”고 전했다.앞서 지난 2016년 미국 경제전문지 포브스는 전세계 남자배우들 몸값 순위를 공개, 존슨은 1년에 출연료 6,450만 달러(한화 약 970억원)을 받아 가장 몸값이 비싼 배우에 오른 바 있다.드웨인 존슨의 열정이 담긴 영화 ‘모아나’는 오는 7월 8일 개봉할 예정이다.김나래 기자 / 사진= 영화 ‘모아나’",
      "thumbnail_url": "https://img.tvreportcdn.de/cms-content/uploads/2026/06/17/cd3c9a66-8db5-4478-822f-05fd0d80659b.jpg",
      "category": "K-pop",
      "priority": 2,
      "collected_at": "2026-06-17T10:30:51.859136",
      "status": "unreviewed",
      "evaluated_at": null,
      "score": null,
      "filter_reason": "K-pop 키워드: 컴백"
    },
    {
      "guid": "https://tvreport.co.kr/uncategorized/article/1054625/",
      "source": "TVReport",
      "title": "박명수, 유재석과 여전한 ‘무한도전’ 의리…”늘 챙겨줘서 고마워” (‘라디오쇼’)",
      "link": "https://tvreport.co.kr/entertainment/article/1054625/",
      "published": "2026-06-17T08:38:34+00:00",
      "summary": "[TV리포트=이태서 기자] 방송인 박명수가 유재석에 대한 고마운 마음을 전했다. 17일 방송된 KBS 쿨FM '박명수의 라디오쇼'(이하 '라디오쇼')에는 그룹 보이넥스트도어가 게스트로 출연해 입담을 뽐냈다. 이날 보이넥스트도어의 명재현은 \"보이넥스트도어가 박명수 라인인",
      "content": "[TV리포트=이태서 기자]방송인 박명수가 유재석에 대한 고마운 마음을 전했다.17일 방송된 KBS 쿨FM ‘박명수의 라디오쇼'(이하 ‘라디오쇼’)에는 그룹 보이넥스트도어가 게스트로 출연해 입담을 뽐냈다.이날 보이넥스트도어의 명재현은 “보이넥스트도어가 박명수 라인인지, 유재석 라인인지 이야기가 나오더라. 유재석 선배님이 명수 형도 본인이 키웠다고 하시더라”며 말문을 열었다. 이를 들은 박명수는 “키웠다기보다는 같이 윈윈한 거다. 키웠다는 건 좀 건방지다”라고 발끈해 웃음을 자아냈다.명재현은 “가만히 생각해 보니 명수 형 라인도 결국 재석 형 라인으로 이어지는 것 같다”고 말했고, 박명수는 “재석 씨 너무 좋아한다. 재석 씨가 있기 때문에 제가 여기 있는 것”이라고 감사의 뜻을 표했다. 그러면서 “다 장난으로 하는 이야기다. 재석 씨가 콘텐츠에서 내 이야기도 해주고 챙겨줘서 늘 고맙다”고 덧붙였다.유재석은 최근 채널 ‘뜬뜬’에서 보이넥스트도어의 태산, 운학, 명재현과 함께 박명수를 언급했다. 해당 영상에서 유재석은 “저도 명수 형 좋앟나다. 지금은 같이 프로그램을 많이 안 하다 보니까 항상 좀 보고 싶은 형”이라며 “우리가 그런 또 서로 간의 끈끈한 애틋함이 좀 있다”고 전했다. 이어 “‘할명수’에서도 그렇고 본인이 하는 콘텐츠에서 우리 아이돌들을 많이 만나니까 공연도 또 혼자서도 많이 가더라. 초대해 주면 고맙지만 다 가기는 쉽지 않은데 명수 형 진짜 자주 가더라”고 치켜세웠다.유재석과 박명수는 지난 2005년 첫 방송을 시작으로 종영한 2018년까지 MBC 예능 프로그램 ‘무한도전’에서 좋은 케미를 보여주며 시청자들의 많은 사랑을 받았다. ‘무한도전’ 종영 이후에는 사실상 후신 프로그램인 ‘놀면 뭐하니?’에서 가끔 재회하는 등 현재도 좋은 관계를 이어가고 있다. 이처럼 여전히 ‘무한도전’의 영향력과 위상이 높은 현 상황에서 박명수는 최근 한 영상에 출연해 ‘무한도전’의 시즌 2 가능성을 묻는 질문에 “안 될 것 같다. 시청자분들이 좋은 추억으로만 생각해 주셨으면 좋겠다”고 털어놔 아쉬움을 자아냈다.이태서 기자 / 사진= TV리포트 DB",
      "thumbnail_url": "https://img.tvreportcdn.de/cms-content/uploads/2026/06/17/85fad2b2-9bfa-41b0-ad09-1e4e2bfe08a9.jpg",
      "category": "K-pop",
      "priority": 2,
      "collected_at": "2026-06-17T10:30:51.860503",
      "status": "unreviewed",
      "evaluated_at": null,
      "score": null,
      "filter_reason": "K-pop 키워드: 보이넥스트도어, 아이돌"
    }
  ]
}